{
  "success": true,
  "data": [
    {
      "mgdbId": "",
      "pID": "7b9f64d84b529401",
      "title": "阿贾克斯vs本菲卡",
      "keyword": "11月26日01:40",
      "sportItemId": "1",
      "matchStatus": "2",
      "matchField": "",
      "competitionName": "欧冠",
      "padImg": "http://catvod.hxfrock.ggff.net/爱奇艺体育.png",
      "competitionLogo": "",
      "pkInfoTitle": "阿贾克斯vs本菲卡",
      "modifyTitle": "欧冠 阿贾克斯vs本菲卡",
      "presenters": "",
      "matchInfo": {
        "time": "11月26日01:40"
      },
      "nodes": [
        {
          "name": "阿贾克斯vs本菲卡",
          "urls": [
            "https://mgev.188766.xyz/play?migutoken=535ddc0c10a3efdf73f41187a28a01a9&id=xB8XGdyHlbdqC4UgDYdRsDIOA24Zz3EHM62jQ6Me%2Fororp22TR7Kf9Q51JZnuxiGd9phLSHDk5LCYjwmViDkodQ3DVlP2u1%2Funv0Zyh0rYv0NXJrEdC3JiWK8Rxricj3EerHOVDjlur3xnIWbOiYmKH%2FAuYecgxlkFkP7lCbsUlqNd%2F9V7ZkFDIHoxwOKflPyiYEq31ZZXYNJQWnWbYpl7%2BMIRI%2FtaFfQCkYnw9MGisrfmnagw9HQKkf4w19kCZDnUcwZZYrMXylh1YjMQo8wOToWqcCOIdGR8kpMtzao0%2BW6rwAwwECC%2BfvNAKgC9af%2BTdyhYN9xnJ%2FPuqALyl2z9NViu9dUGSQOz9OmWHrtYxYC9kbSDElo0i3JCmhz8trXqqSGXHq8%2B3YY1hXFunpJQ%3D%3D&name=qc%2Bqy2Fyh1da2DDh1oK3H0d2Izk7fa0eD3couwrcj6dGbUSOTYNUcKHkXz%2FyBqVd21768pR9Yy%2FEkPreOahYVg%3D%3D"
          ]
        }
      ]
    },
    {
      "mgdbId": "",
      "pID": "4c012152dde60c1f",
      "title": "加拉塔萨雷vs圣吉罗斯",
      "keyword": "11月26日01:40",
      "sportItemId": "1",
      "matchStatus": "2",
      "matchField": "",
      "competitionName": "欧冠",
      "padImg": "http://catvod.hxfrock.ggff.net/爱奇艺体育.png",
      "competitionLogo": "",
      "pkInfoTitle": "加拉塔萨雷vs圣吉罗斯",
      "modifyTitle": "欧冠 加拉塔萨雷vs圣吉罗斯",
      "presenters": "",
      "matchInfo": {
        "time": "11月26日01:40"
      },
      "nodes": [
        {
          "name": "加拉塔萨雷vs圣吉罗斯",
          "urls": [
            "https://mgev.188766.xyz/play?migutoken=a93d6f4aa34d7bc09ee286365bf8c90e&id=7uNDs%2F45BxQWKUENKZX4kATYqHihYgXWX9MplHD12qNzMtriHoi8R6wpUWjnFzMaregTCTQty4p%2F5rMwy3%2BUcUKweQKQ4ybU6Ef7wBNl42ntgUFIE%2BVwjU%2F%2BKV%2B0%2Bms6wuqrU9cRqSqP%2BbM2gmoEpR6sUr6cMcvWf5rqJYvnPt%2FHWhpiUqqWNfhSjNPOKb6SZDQ8uVf%2BS2S%2FrhRpSS2h2ooNvhi2%2Fv%2B5rVCwlBKgYlO7T6%2B%2FEBxj4AMzScmYglS6TbobbBFZstap3mKeRmvbdTxPxEs2Ammf3%2FgY2k%2B5WHRzAK41FVnR4egUeKPjPk3FkS%2FT0FTujPa957lkVAOuBgkblt2CfjQtGWfYsygip57wAVdG1zEKC%2F0nTqNksXl9YJT4cvLHWWgdH7cml7lNWw%3D%3D&name=nL7NXnhvVR%2BeRkX%2FqHuXdpU7eVc6mDvZJYkQVArmKQrnArDKcL507%2BwJ1lVkYO8MBOazD%2BtCq%2F9Qtp5ZQx5eDCm0JgaZ1RLXmzT3LhPK70I%3D"
          ]
        }
      ]
    },
    {
      "mgdbId": "",
      "pID": "62c4da423d430ecd",
      "title": "利雅得新月vs巴格达警察",
      "keyword": "11月26日02:10",
      "sportItemId": "",
      "matchStatus": "2",
      "matchField": "",
      "competitionName": "亚精英赛",
      "padImg": "http://catvod.hxfrock.ggff.net/爱奇艺体育.png",
      "competitionLogo": "",
      "pkInfoTitle": "利雅得新月vs巴格达警察",
      "modifyTitle": "亚精英赛 利雅得新月vs巴格达警察",
      "presenters": "",
      "matchInfo": {
        "time": "11月26日02:10"
      },
      "nodes": [
        {
          "name": "利雅得新月vs巴格达警察",
          "urls": [
            "https://mgev.188766.xyz/play?migutoken=41d274276dc39ba2c5f07477a25f8c61&id=qwtjnSYZrmSnlyydfgwNk4MA8R9fc547x6GPTm2%2Ba4lJEl98gs6%2Bc8kY6P2aHVhJ4sYaVrqSfxtV78IXbhzKCG1calSNPp9nX14QPWo1rTdcyZBqV4gKhI7X%2BaG2i3ovbdoootFvY3n3d8WzgaoI%2BK%2BSnFMB8YEkACuBgaBvGkk5JJQwfHw7VfeY9rmKbiLDqWxCqExCDpiRtZQ0Lvnzne%2FxA8MuG7dV165%2Bhy%2BeUvJDcjoRJJMbjyegdPmEj2zg4D2vWL%2FcMoiX3iN9TZvTYiqhhG4G%2FhE6I2bOY27lhpxrgz2gQrTSgmopRqbEtr3rP1c%2FyIXf8dfM%2Fyp9vfpyQnLTdhJCsgavTUw9JY7Ddl35R35hcmPGGH%2FTWJVw1WK8gsfRVezySCEHzrOhmWBoFQ%3D%3D&name=zno9hFk7qRU15nVxea0c%2F5DZaLxR2xITbkpgsX2Es6iTz6PFO4td1AWieAJjd4dl504sR1nvSkHnkI5Y%2FcmaT2o9Si6Ny5kjHOwoGjtyz4M%3D"
          ]
        }
      ]
    },
    {
      "mgdbId": "",
      "pID": "c1f2476aa5407311",
      "title": "切尔西vs巴萨",
      "keyword": "11月26日03:45",
      "sportItemId": "1",
      "matchStatus": "2",
      "matchField": "",
      "competitionName": "欧冠",
      "padImg": "http://catvod.hxfrock.ggff.net/爱奇艺体育.png",
      "competitionLogo": "",
      "pkInfoTitle": "切尔西vs巴萨",
      "modifyTitle": "欧冠 切尔西vs巴萨",
      "presenters": "",
      "matchInfo": {
        "time": "11月26日03:45"
      },
      "nodes": [
        {
          "name": "切尔西vs巴萨",
          "urls": [
            "https://mgev.188766.xyz/play?migutoken=a788dd0dbff277f5709bf4230b323bca&id=Zeho4k%2BAResF7XfBucoPeiH%2BnURSQ84uM1xg8vW1g8s3YKfKOoYPSr2jgqG4BFU6J3EGsLZq6Llabb8A84%2FLAekUTUTHwk%2FvwmvfOuTM5e3g%2FnaxxGUtQHY7%2FAIJjDHEANlACGraZ6mQTEFnQV%2Fhz3CrtXEwU0e4ccstOagUmbwmOl4GQWf14LVsCe3zgf3Er%2FDPYmrcmJ%2FT6dJj2ipCyCNeHrUm6bMUz5xYoeUFMkhrVeV5hWE%2BFfH%2FwBCoy4opy19CZUcjhbCEB98LUvaNPUmgTOg6fvVqrqaR29LQe0i2%2B7u4N0e%2BC1zV8jp0U7QlX0iZjCCrMiNVSPg0tG0qf7KAJeQ5oXsn2PT8X%2FZZ1qmvSahlZgA5Dnnl%2FskuuaAJPyB5uHHuC7lRcu2P3l8Sqw%3D%3D&name=llmvvT7C36uZng0i2G6Yht6SMha5IWug44CmnhfhSEntD0m4Osfe7Qxo6EOul%2BsHYoEemyeCITLrly%2Bhlfv%2FKw%3D%3D"
          ]
        }
      ]
    },
    {
      "mgdbId": "",
      "pID": "4605db66d2e9c977",
      "title": "曼城vs勒沃库森",
      "keyword": "11月26日03:45",
      "sportItemId": "1",
      "matchStatus": "2",
      "matchField": "",
      "competitionName": "欧冠",
      "padImg": "http://catvod.hxfrock.ggff.net/爱奇艺体育.png",
      "competitionLogo": "",
      "pkInfoTitle": "曼城vs勒沃库森",
      "modifyTitle": "欧冠 曼城vs勒沃库森",
      "presenters": "",
      "matchInfo": {
        "time": "11月26日03:45"
      },
      "nodes": [
        {
          "name": "曼城vs勒沃库森",
          "urls": [
            "https://mgev.188766.xyz/play?migutoken=9b2154142cd04501368717be11d0c70f&id=gZawelnHz4AedUkd82mM3lBgrCzbBxEl2XKOPyz%2Bj0dLBD6poXooB8oTzoegY2pQEX6wxJQB9d4yvWM0A%2B8Zc%2B2delnEB0A%2FdZu8%2BexfJe%2Bvn3D%2FYlw%2FS%2BYQ1JUS3JchVEltzJEY%2BDlxCutKYUhsAxLQF0Nb9eJMnh5%2Fi2FRh52%2BT9jGf2qvy%2FL4cIN2ztbVFUOdY2JXYtJ2bBkqbbZgKH7lA0y2zP5Q%2FL16CZMK6FkzcBxc%2FsEpHZjE6P5kCONY4vWOyMHPZUGMhF%2FQOPIBhwfn97pTrYQQ%2Fozlx8BaKQ5weWe5Wt1EAszf0AvxKA9mnfpMzmmQM0R84TGs3DaLhx%2Bs0VDNhXoqumIG0EDgvGT12s%2B%2BjFlP1l1YXKcqC83yV2N%2Bzhywyqy%2BMznpXdWxiw%3D%3D&name=0S92shpvm0xKdXRjl70OZ7JiqrvyTI6Nc2DHdKS4AY%2F0e6KW9JaIfgCxEmeB6u66Wg7fAU7J59xlkAQieTsabQ%3D%3D"
          ]
        }
      ]
    },
    {
      "mgdbId": "",
      "pID": "80bdb97b09f94afd",
      "title": "多特蒙德vs比利亚雷亚尔",
      "keyword": "11月26日03:50",
      "sportItemId": "1",
      "matchStatus": "2",
      "matchField": "",
      "competitionName": "欧冠",
      "padImg": "http://catvod.hxfrock.ggff.net/爱奇艺体育.png",
      "competitionLogo": "",
      "pkInfoTitle": "多特蒙德vs比利亚雷亚尔",
      "modifyTitle": "欧冠 多特蒙德vs比利亚雷亚尔",
      "presenters": "",
      "matchInfo": {
        "time": "11月26日03:50"
      },
      "nodes": [
        {
          "name": "多特蒙德vs比利亚雷亚尔",
          "urls": [
            "https://mgev.188766.xyz/play?migutoken=d1c174a686c1e03f02c39f9dcc7c6e6a&id=F%2FbKpBUW2f27SgVKfbmWI4SuRoLguKj7VHxajVXXBeeqBsdoEYenJ92E7odxyxJ%2FxV%2BdIaLqX50TA9EjKxMlCFvODE16juDlkkkZM9JT4Ox6mahrtlt53WeOT9PkBcn1037sHRvsB7knnbX4uwbFnkCOYqDDVUF0GTHeRKGbJTnfChSK6Q9Egc9FhTeCuPW6skiSMxKBweBDWoISk9nO0EYHi6vU7nTSlOs0i8P%2FrPQwTwV8gk8uS1X%2BU4otsTIvWLf8pHgJlJYj2qixlj1aSVh1b7qIw0Glb8RRj3M6xdQFZXKjU3SDebUmfO%2BX6GLMnQdSSF3FYurXoQ9yY2T0twdYRT9dZ1apEaimG1VDoF64FjzJankHBYl42tS7367vJoEphV9RnOEf5KK4WUpdZQ%3D%3D&name=jUFhlITrf4DV%2F%2FELw%2BifN1%2F%2BmZFmMwfmH5TFSPE9UX6UFfRgVFmFEzeQ42bL73OLnzZ1PoujyQveWlBNQObsDt3sRQY66sR0Jnbpa0YkHDc%3D"
          ]
        }
      ]
    },
    {
      "mgdbId": "",
      "pID": "2999fc8d0771923d",
      "title": "博德闪耀vs尤文",
      "keyword": "11月26日03:55",
      "sportItemId": "1",
      "matchStatus": "2",
      "matchField": "",
      "competitionName": "欧冠",
      "padImg": "http://catvod.hxfrock.ggff.net/爱奇艺体育.png",
      "competitionLogo": "",
      "pkInfoTitle": "博德闪耀vs尤文",
      "modifyTitle": "欧冠 博德闪耀vs尤文",
      "presenters": "",
      "matchInfo": {
        "time": "11月26日03:55"
      },
      "nodes": [
        {
          "name": "博德闪耀vs尤文",
          "urls": [
            "https://mgev.188766.xyz/play?migutoken=ea70f883a0d5061e6bc46a26c979a418&id=CQQHl4f5R33%2F13lj9ZaTm5KPa2%2B5%2FFu6vC%2FODmxA3adncQ46Ni%2B0zNWqYLn3h8X2JpDpjq4TkELy2336wtdxZmOaFBbRD5BfhOUtJJJhhNIX1OjfMEyqfXLDNkeRgOCxk%2B8f2pM710gk6WKjg9MHbP5vV7HgZxj6kJba%2BmyW%2BKAgqIUBFr7W1VMZRMISfVV%2FdIbDSlgozPO7D4Iimidk2Pa6kWxBlNJUQGGV0E%2FTbSDXol9YUW6v9u2eT8nIgwrhHCAyWfMbJlLHO6SKUlDHcLX7Sopgi4LkI2lIaLooBqc297m0o5YFC03h7X34NmPn240biJRmJT3SABEaG8%2Bqn3GwmTHaIFF4bX6fczthG3yg%2F4GxrMbfJgCm7EPjPMT7iKsQf%2FJSTX09ajikl9SRAg%3D%3D&name=ZvBUZiqn8M1HsDJ7rQUJ%2BwfG5zWEOZ592pWln8ergd5QEYcS35GWfqG0QC3mKh820rp3G3S5izquP81iz7GkAA%3D%3D"
          ]
        }
      ]
    },
    {
      "mgdbId": "",
      "pID": "3fa16a44537143bd",
      "title": "马赛vs纽卡斯尔联",
      "keyword": "11月26日03:55",
      "sportItemId": "1",
      "matchStatus": "2",
      "matchField": "",
      "competitionName": "欧冠",
      "padImg": "http://catvod.hxfrock.ggff.net/爱奇艺体育.png",
      "competitionLogo": "",
      "pkInfoTitle": "马赛vs纽卡斯尔联",
      "modifyTitle": "欧冠 马赛vs纽卡斯尔联",
      "presenters": "",
      "matchInfo": {
        "time": "11月26日03:55"
      },
      "nodes": [
        {
          "name": "马赛vs纽卡斯尔联",
          "urls": [
            "https://mgev.188766.xyz/play?migutoken=64284298dcfb2abe7b61721224eed9ab&id=WXnaKKiDkKxOmDsJJxD83lC%2FaYWhoB5kiO0jSf%2BU9JOefUyrxeNJXlAwjfEK0l0GIDjGP0J532MPXgR%2FPCG2K0ddVsvIVfPuoAY%2BG7EXHxAyjnkLXLk2VdFSycww1h477e1B1%2FxG%2BVwUmCTD73mY2Nm1%2Fj80PNu%2BpdtZainCjbZrgo%2Bfb%2FTf9oBicT%2BNZbkD1FWaxFp0CdPvqwJF5TUmIUrNGxXSMsnWRtt%2BWJJ9wlGg%2B3fQILLYlm9%2Fp7M3GwVjgLXHhvqEj79MwXIrszRhMrLHid7DZqoMbkzL0sE8EWAGljpUQPxhRvsah6pVtvwyhLmRzZBb4EUYAC7z64TNrzlWwg2N0KHb%2FhnHuVHmbMLTl4Hjh%2B4kjUds3YPcXb53CNupMkwBp9TVZNOyl5C%2B5Q%3D%3D&name=G0a32k32zgDlavFJuh1ahzgB0GEhUfZCYpCocKWqbyyr%2FI4bN6GyN%2BpjwzCP%2BhTu3cfcAkfbb7OzDSjoa68UXg%3D%3D"
          ]
        }
      ]
    },
    {
      "mgdbId": "",
      "pID": "0f4076118c849be2",
      "title": "布拉格斯拉维亚vs毕尔巴鄂",
      "keyword": "11月26日03:55",
      "sportItemId": "1",
      "matchStatus": "2",
      "matchField": "",
      "competitionName": "欧冠",
      "padImg": "http://catvod.hxfrock.ggff.net/爱奇艺体育.png",
      "competitionLogo": "",
      "pkInfoTitle": "布拉格斯拉维亚vs毕尔巴鄂",
      "modifyTitle": "欧冠 布拉格斯拉维亚vs毕尔巴鄂",
      "presenters": "",
      "matchInfo": {
        "time": "11月26日03:55"
      },
      "nodes": [
        {
          "name": "布拉格斯拉维亚vs毕尔巴鄂",
          "urls": [
            "https://mgev.188766.xyz/play?migutoken=304125da53e58a480b37df4581aceaaa&id=L01zQPtgWMi6p0v29G4m3iQ5RHEMljm3MR2M%2FOcTy4G9nLXR7o6rl5KESdqjjm9mNhb2zg0kaFacbt4V6rbG%2FMHqJ2sW3RIvDH6%2BtfahS7D9eXYrbE7t9oZ8GSDk1qSBDbPQ9jZJKwBuxZRTTugaGYZbMZ0BniUeii4SE3EoHwWdbntbeltHDoTH6V%2FaFDHzTtScbQYcgbA6mPMUjtFbjp6nf9HJVEJtdeHeez%2FZ6BJvSLGCafm3Nl80eFIdKQ6wIEjdk7i%2B%2BoYFNT%2FVAwfbuU39eMf7fb0eJzGmSoHiiSXD8amBBPmQ6c8tG0W4xqDEm7Dli45MYBHSN6ot%2FuP7bNTCVevy2sB6XTmuz7R3%2B4xXx%2FZ6VZ8Aq3Bji0pDJpd9wygmq6o5d2Q06OWNiJSF9A%3D%3D&name=enY11NQa03kQxM20mXVT74abSlGMD%2FDPy9fmXKNen%2BW3lUJ6W24UTdMyUpSHreLdFUFSNAd%2Fkthj3yxzNmkxhEuPIVM0f99yErDC4yDiaqA%3D"
          ]
        }
      ]
    },
    {
      "mgdbId": "",
      "pID": "e9732e23054140c8",
      "title": "老鹰vs奇才",
      "keyword": "11月26日08:00",
      "sportItemId": "2",
      "matchStatus": "2",
      "matchField": "",
      "competitionName": "NBA杯小组赛东部A组",
      "padImg": "http://catvod.hxfrock.ggff.net/腾讯体育.png",
      "competitionLogo": "",
      "pkInfoTitle": "老鹰vs奇才",
      "modifyTitle": "NBA杯小组赛东部A组 老鹰vs奇才",
      "presenters": "",
      "matchInfo": {
        "time": "11月26日08:00"
      },
      "nodes": [
        {
          "name": "刘乘源",
          "urls": [
            "https://mgev.188766.xyz/play?migutoken=49569a859ce804c440f94a538fbb3b39&id=nlSGN9KDm47fgE%2BUXeXVXlGYRPv2aiNU%2FUzXkweYN13uHO1NfYBwOCUcwlIZwSgGhKcuJzyCXxMqwCPtlM8t2Wx6%2FB7tMxYjU1WlbMRh4DCxmF1XS1%2BGBX4Tm6GGnaU2OXRjcn4HiC2uh0vaHoKwWUNpJcn%2F4iasbyMwV%2FkU5818IKXOYbthtaqYmEPajB5hpkZJBkFGrk3I20Al8uoGEhmykoaHhdi2CljB3dU3P4f76k3cgyjHghAj%2F59n1hi7hWDM9mH6Aq91fOSRpOolnDERhNmoyBceToOFL72rI48%3D&name=yxVEcKHMoXIBC18sAI7dPQwsaCnqxP701hn5uNVVy%2BXvqc4LKCq7Pn4nc6yLHA3y7oLnMox2bA61fxT4oOsgm2syQTbURGspFzhSaDxIkDF8iJEDufTY37xiP57ASqP1"
          ]
        },
        {
          "name": "英文原音",
          "urls": [
            "https://mgev.188766.xyz/play?migutoken=4211ca30a3901fa3f9cc92ab0e02a666&id=BKR1iSfhTGrG7NSFBlymsfuIQfvin2OYhfXDrNOPgzAiQeZKDVYPWhrtHvd9pPBwlxv4D%2FlKtf4Gn9m7nf8aNE58GhVHMlwepgvXe%2B2YlIR%2BuySTtmKHIxZPjjUrhcf7NpCywAYKg7%2Br9rCLO5NzchDbkm79rfQjRMMaMyLjMTCylL3fvBy52dXWuOClWdHUwjjHJ%2BdDUGUA6kqnXMqkzLthuQha3v%2BIEJg32K%2BhZO3g8gMwpgJIhpbe9Hokiokk2uR69V%2B33FuDKp5Fi%2FEwwls5Z259Zdoc%2BdXUKT%2B1c8I%3D&name=FoN%2Bjw78iy8qPRbwtBaWlWhiCQ8gsIR37Xl5aEevlMfjiF6aYHU88Qcz%2FFVrKD5NY9PQ9URZh8oU1yg%2Bx6PDmXyl0RGfu3oHLXm087LB7hF28G4o7QSmj2ch5dSmgOG8"
          ]
        }
      ]
    },
    {
      "mgdbId": "",
      "pID": "22a4b8d6aa7bc4f5",
      "title": "魔术vs76人",
      "keyword": "11月26日09:00",
      "sportItemId": "2",
      "matchStatus": "2",
      "matchField": "",
      "competitionName": "NBA杯小组赛东部B组",
      "padImg": "http://catvod.hxfrock.ggff.net/腾讯体育.png",
      "competitionLogo": "",
      "pkInfoTitle": "魔术vs76人",
      "modifyTitle": "NBA杯小组赛东部B组 魔术vs76人",
      "presenters": "",
      "matchInfo": {
        "time": "11月26日09:00"
      },
      "nodes": [
        {
          "name": "孔德昕",
          "urls": [
            "https://mgev.188766.xyz/play?migutoken=7db6d4d845dbd6c6c941e7f20527291a&id=uPhV9ylkj6gOHQcK8ymgkdXStZVZQNUGR5fedY0cdtYSl8fSGcO6GNE1XyT%2BkWD1%2BBhTUnszrrh0vtzsr%2FwnKURW3aTf%2BlLQh%2F4gZgDrycTiLkJG%2BNiw6L3OmLVxT6%2BX6C6sFYdEo3N5ZWeKIlXQS1NIn3sq%2BJH0Ilt1sCvhJZlqtbhcCXk%2FvERAF37m1rEdbLnCpoA3s0sH3qSvjNA7v7UiJxz5%2FNCbELMX9f85CXcaW4bPDS%2F1GRgH7SZ3Pr2Vt8vLaYi%2Bt%2FxOZyAuOk1%2FU3cwx0jZxQR%2BqnR63BqO9qlz7WUB%2FusIMI8%2B1HFd08o5039DR8R5wN7%2FiZIVD7XAyg%3D%3D&name=BtpdViNgYpE2Xir%2FIJ1XUS%2BePzQk2rGAC4nIysUVIPV6wZDRK8Yg49Ap0F634Jm9Xr54L1CCkd6KnAtf84dGbmG%2BreMXjOzYjuNF2DioKv1VNsNEhGwBMSmZPukAyjK7"
          ]
        },
        {
          "name": "英文原音",
          "urls": [
            "https://mgev.188766.xyz/play?migutoken=b46e4ccbdd60ff436345d4ead836dcd9&id=Bs%2FuH3Z3kZLyTHX1VPAt6bahd0KtV1CI4SAXfkpNAMql2ds%2FvJcBGc%2FIxauZn6Psp35aOPilA7aoJFTgA7DEXBRCm2XB8IsbsIFvxs05Ppr7qYzRP1g4u87vIYgjpfLOpe%2BxO2iyayeO%2Fwu530n11gFU6hrP7EjXvht7dC9nYo7E5vS9ex8Came3S4etKd2NCeJdMNSGjDL6I9uVgptwr3gDXtX4Dz2b90odkSuI13EUCZwB7uSF2fFcIPJ26neX7rFY8qb6ppVBUiW0J3xgRrv8ps2laD3JYXlDzAMtPEYok08yDzITRwiazxOMD8%2B79WHmpqFldVmlQYhZ10FZQQ%3D%3D&name=aHY2A4N6lkGWbMjJzHg7mHu6g%2BJKfQVgzdsrwy4hYdmdJfvu6LQCxyikAkX0p3fdMAPVBUXZ17LAuQM3ja%2BRXAzTKgEYWK16u8IaycaXJ18L4F%2FZb7evuXrkjzChQiXM"
          ]
        }
      ]
    },
    {
      "mgdbId": "",
      "pID": "17adfbcff1542a1c",
      "title": "合肥文旅vs福建厦门白鹭",
      "keyword": "11月26日10:00",
      "sportItemId": "2",
      "matchStatus": "2",
      "matchField": "",
      "competitionName": "WCBA季前赛B组",
      "padImg": "http://catvod.hxfrock.ggff.net/腾讯体育.png",
      "competitionLogo": "",
      "pkInfoTitle": "合肥文旅vs福建厦门白鹭",
      "modifyTitle": "WCBA季前赛B组 合肥文旅vs福建厦门白鹭",
      "presenters": "",
      "matchInfo": {
        "time": "11月26日10:00"
      },
      "nodes": [
        {
          "name": "合肥文旅vs福建厦门白鹭",
          "urls": [
            "https://mgev.188766.xyz/play?migutoken=0ff4a308dd5bad83f865386d82f41cc8&id=iUetvEeWFFalNhjV74PafHq%2BV9aWNYQXUELoNoyuIXWyTXtN5q0BxiwW6AcjUIxDx3GnCe3AOL8zuxcpIAd1ZmLcAUyUfBZz0mPwSoq7GRTpdnHHmyp%2B9fyZOrXvBqdlmiPQc%2BztGMrfjLNgGhSQ%2BEJKd5SEidHEf1VamUcnFOVPn11FfrjhacLoG%2BP6XkT%2FkJiMU9GrY%2FpjZATp2SFXRDCLsdMlznqQbQS92TIf0ZJZinr84MqlKwaDwrdsAXP3DVCSp%2FbqZ2%2FTD%2FimHT54XMLBkUw17Ej9RzF%2BGHh%2BzxJX5e09NM0sk6LR4orNsOul&name=VGjmBDcCEj38gUFyVUVcnIlqEVH%2FkosG4wfIjy0ZFCxVfRfOkmPotL37zJucrUNHsVmvfPawiNIF%2B%2FaWORC9twGlNT3moQ9wfyUn0y0nCUr2zWaRK48AXLyZTcDoRl8V"
          ]
        }
      ]
    },
    {
      "mgdbId": "",
      "pID": "e1614a397efbbf2b",
      "title": "北京首钢园vs陕西榆林天泽",
      "keyword": "11月26日10:00",
      "sportItemId": "2",
      "matchStatus": "2",
      "matchField": "",
      "competitionName": "WCBA季前赛A组",
      "padImg": "http://catvod.hxfrock.ggff.net/腾讯体育.png",
      "competitionLogo": "",
      "pkInfoTitle": "北京首钢园vs陕西榆林天泽",
      "modifyTitle": "WCBA季前赛A组 北京首钢园vs陕西榆林天泽",
      "presenters": "",
      "matchInfo": {
        "time": "11月26日10:00"
      },
      "nodes": [
        {
          "name": "北京首钢园vs陕西榆林天泽",
          "urls": [
            "https://mgev.188766.xyz/play?migutoken=c73081cea83063b4f59f0747106a0f8c&id=ZQCVJBJ%2BqbD3RnNUDnWflsb%2BqKiZFZQczVSUwCgUcBYK8TRFPvB6u3X%2FwQIwTZTKv%2BW8ohvYoAAWS1mrDLyUljkOdqY3Vw0FtA%2F6nAxkqLYljSrWDHdm2PEZ2gfTIM1ky9JkeW0MspB%2BNxrkOx9Vof5FxCw8%2BJLSBWJmR8jJvpp2B9YnsVvfHDYqqWaKvKKMvOHbLBF1FZSzYuFyF93Y5Xu7DcwGFI3YKY91NJ%2BLrkW6cBntynx8jYvQThi1Dkm5x6BcAf5xRrMvIxY627Yy3L1nHh41zZsB2v5gROu%2FpNx6jnk6sfBwOziQmz13m5hB&name=KnHSSFBjfXd19VzBZadzOf5yTYdODh4IUmqladPD%2FRdvK8mOKDJCKVXA1YmVAqspxSl0zCZoxgaG6X2OClp0EBP93uh%2FRI3oqLFK99zNMYbIdDsJ8CSND0Cla1qFNF1z"
          ]
        }
      ]
    },
    {
      "mgdbId": "",
      "pID": "b29b09f96d693044",
      "title": "[早安Tip_Off]第36期",
      "keyword": "11月26日11:30",
      "sportItemId": "2",
      "matchStatus": "2",
      "matchField": "",
      "competitionName": "篮球直播节目",
      "padImg": "http://catvod.hxfrock.ggff.net/腾讯体育.png",
      "competitionLogo": "",
      "pkInfoTitle": "[早安Tip_Off]第36期",
      "modifyTitle": "篮球直播节目 [早安Tip_Off]第36期",
      "presenters": "",
      "matchInfo": {
        "time": "11月26日11:30"
      },
      "nodes": [
        {
          "name": "王猛 孙悦 美娜",
          "urls": [
            "https://mgev.188766.xyz/play?migutoken=593893c0302d0594c6be9d417f493f31&id=%2BFU6XT0qdq0QLKsh8cXBmaa8owk7AaIdO8oqoIjEJoCBT6pC02M%2Fu6TedDRwXX2uLdiQ2LGzcmyouCJ9MssG2pSuT84YRk9VzbvXD%2Bpy4p1VhuMTCgRslXFr%2FYYBebT%2FuYQc3bGAURaGvs6Kt89GjhNV5%2BRv6aH%2F8ZNWA0gW3%2F8t49DvbdbD%2BWIWVTW9NPLXIJdGi8kCNnPGAGcEY25n%2B0kTEKYkD6f4BCgswmnPs8uwuInFJ7RvnRhz%2FTjyl8uV1uSwdrKNfN9%2Bg5lKXrfZmBVhmfmoB%2FTr6fBxNiaV2Rba0P92dWmYgHi6PnTSr4Nv&name=CvIbBFrcCdjf5qnq8XKma9p39bd30uRer7ifBjgBgH3as%2BIBLhdvwtbeQs56KuB7zBZlCp2BTwddFADHz7qkEA7G6XHWp6lYr0785wVtPSOCtqGs%2B%2FG%2BsDthZxK%2FwpaH"
          ]
        }
      ]
    },
    {
      "mgdbId": "",
      "pID": "4bfaaad8b71b4c9c",
      "title": "快船vs湖人",
      "keyword": "11月26日12:00",
      "sportItemId": "2",
      "matchStatus": "2",
      "matchField": "",
      "competitionName": "NBA杯小组赛西部B组",
      "padImg": "http://catvod.hxfrock.ggff.net/腾讯体育.png",
      "competitionLogo": "",
      "pkInfoTitle": "快船vs湖人",
      "modifyTitle": "NBA杯小组赛西部B组 快船vs湖人",
      "presenters": "",
      "matchInfo": {
        "time": "11月26日12:00"
      },
      "nodes": [
        {
          "name": "王猛 孙悦 美娜",
          "urls": [
            "https://mgev.188766.xyz/play?migutoken=ff66542cef71a9b41c4b1e745c131e66&id=h9Vwi4f%2FlsTZcssS%2FxKM7pqSAW%2FxN5J6ysmJKv0lJBG5JazzmixIOpK4p2F7d0Aqk8JL5Q9WUP1fXejvvjmvMAkn5rOaom3WsYJPnPM%2BDz6Duem0vdRj5RbMn1V48dQtOsVXWRV3HKe4y2SR0TfZ3XDEUfgbm0HNl0Iiis5XclD5%2BCOSYUttLQOeXdlIPPq4b5dXnSXG0Ply2QVerrLce3jRRFdnkUZICr2uelve43RahwRGgNTc0syRAD%2B8F%2BuzG0WHFoORGMKRMHNtHokpfrLVZNYUboiqlRrPp%2FdYgDLKaCBsMuK0X42UedRgrLrNU2yEzP4EYn8Qa%2Bzehs%2Bxdw%3D%3D&name=rjmwNFIh1k5z7yzVB%2BPwWgRcS7j%2B9kVdoh%2FmlokqfAd92ViDHzMLx7vf6sd64Um0hGlxEspeuF2YoAHDOdvOxrS4Y%2BEMWGwMdlz93Io6Rp2Dk24TOOr8MnSwzN7aVWLz"
          ]
        },
        {
          "name": "二路_皓篮球",
          "urls": [
            "https://mgev.188766.xyz/play?migutoken=e2321cffd8bd1cf2b96b93801ac0e37a&id=8GqdW%2BOIrNxohYn%2FcXfcvOVt%2BZtdLxbGq4Gm%2FXsu7a8cIuZrSY2FzlO%2Bwb7%2F6HYrlpntoh5n%2BZ3ZH8ATlhOk4BCqc87hm%2FqfMdSnnGdkbHCm41VCF1d%2FPve6k4u3PRuAC71YFFfhf85zBg7YBCNZOvfUP2XqyvsZmZcCDnERm4cuCvDx3KrE086968y%2FRyHJNLZN5n%2FCemYE43rTzgpJluWYEoXwrfvEwBmZkUMkkjhIXgsyGudGwMTR4HU5tP3x2O%2BKmyPnnzvKtMIdbvR9JlglzA0eTpnzbGHSWQVPqW8ZM2WTCC8Dz1Jj1Bj9CejETLbGAaApO8nA%2BifHTFEpRQ%3D%3D&name=K8jPTL8h7qljLWJUTKyOGd2H3oCZy%2Fm5q%2BiSoUWB2obelsZbzq2t6foFaf7Gwct1aGU2MpR3SQdFteuLQhCcwigSIGjfHoeQe2McN%2FX7%2FnAqznvW8mtHcXCmMoADRfh0"
          ]
        },
        {
          "name": "英文原音",
          "urls": [
            "https://mgev.188766.xyz/play?migutoken=2daba26e88182a05a61ebe6e862905ca&id=caZ%2FQ2KndHyYDX9PC7Wtsfrv064NPs2%2BPH6U%2B0GwYFkjEXrXcQ1K%2BxCIcBTkd6dS43swCU5akoua0MwrfxKiDFb9yGLNY5W72wrzIKommkUQxMivERfwxloKvm3k95uXdXfKbWiTJFIiMMe4froMaxNzvVWpz1y44UD4tqaEBeHaUnF2i3%2Fgsacw9O7wk3pJY7LTYrR8jwxxuXt8hIgBO4YyUQzJopwR9HU8%2BKAhX7P5tEBVh8wuzH7kU73szHo3dN7bcK4ApY75K0J%2B7BaTd8klz44xy%2B5vYoC9DtZlpA8ZCydqItgknvY9vpetCWFRunErpsgbVT5LaAJxoLhKDQ%3D%3D&name=d%2FmUl4RE6zyzw5R2Kr8EXVmaj46ekTDWJfBRjgRiMjbvq0SJdjZ1R8FW%2BFQBhbK7j9FXYI2Qq4Xn4ms9V21X0Df%2FJNT52ZkYeG3fd%2BacF027E%2BjJ2y6xrAxfQolc75iW"
          ]
        }
      ]
    },
    {
      "mgdbId": "",
      "pID": "01a793594f1ebebd",
      "title": "NBA常规赛精彩回顾：老鹰vs奇才",
      "keyword": "11月26日14:00",
      "sportItemId": "2",
      "matchStatus": "1",
      "matchField": "",
      "competitionName": "NBA经典赛",
      "padImg": "http://catvod.hxfrock.ggff.net/腾讯体育.png",
      "competitionLogo": "",
      "pkInfoTitle": "NBA常规赛精彩回顾：老鹰vs奇才",
      "modifyTitle": "NBA经典赛 NBA常规赛精彩回顾：老鹰vs奇才",
      "presenters": "",
      "matchInfo": {
        "time": "11月26日14:00"
      },
      "nodes": [
        {
          "name": "NBA常规赛精彩回顾：老鹰vs奇才",
          "urls": [
            "https://mgev.188766.xyz/play?migutoken=2d89ae3412cf332905fef514a3daa5b1&id=yUl3qQ8pk7k9gvmYq1R7dlZt4LSUzb2axKpxFhEY9L1jX%2BxuLKRl9YGA7bRmIpXh3OaTJ98b98crjCJdasJeTkuALjcPqGzLcgaZiUHxo5Vo3Ncz3ajJQQUblZreR1YFB%2FaCLts%2FHWDBA4GJJNfa3m1LT8v4N%2FygjnMxmEFPb8G4oVOuikxcDr5UUmME4VFiMLRny9AS1qKR%2BIlybagPMKtIx%2FSsC2gEZk6F87nx0FNPGilaTS7BvDmud7C6Z6hnDq5O2VnmYs9CL%2F5F2yZyntGrGxtuh6ceTETfWdiLmMYMtxWSIrWvgtUpI01gr7Qi&name=kHx4QB%2B1P4do06kuMnUj%2FC3ateeg4GSCwdz%2FOhaJrDBkgWlr63on%2B7lx7SE%2FpzDsOZVcqOi6ho9fMjHiFYlT5Jub5oO05kOhbq3iVhyErzAUWu4v5%2BlHgZKKxuuoD7bq"
          ]
        }
      ]
    },
    {
      "mgdbId": "",
      "pID": "bbdf1fc58a4c6f1b",
      "title": "新疆天山vs浙江稠州银行",
      "keyword": "11月26日14:30",
      "sportItemId": "2",
      "matchStatus": "1",
      "matchField": "",
      "competitionName": "WCBA季前赛A组",
      "padImg": "http://catvod.hxfrock.ggff.net/腾讯体育.png",
      "competitionLogo": "",
      "pkInfoTitle": "新疆天山vs浙江稠州银行",
      "modifyTitle": "WCBA季前赛A组 新疆天山vs浙江稠州银行",
      "presenters": "",
      "matchInfo": {
        "time": "11月26日14:30"
      },
      "nodes": [
        {
          "name": "新疆天山vs浙江稠州银行",
          "urls": [
            "https://mgev.188766.xyz/play?migutoken=6667e71db270eb7dac0d72c6b08c20dd&id=cUpzi2Bd4NMShigb%2BgpOWI9YBZBqTSZoAY%2BlB6KB8%2Fm3jKcI0K%2Ft5aHFOVtDmck1c0KpfMgHT8P%2BH3GuUJnz9H6q8AA%2BM7JNWou0fnvex9lqFfONiX5%2FmCj4L6QuQFLuAWUVFaGvcdO6%2BSmkfNwtcwrQsM6rdVaqqIDpBl%2F%2FSoIgob49UkKxTWRxpcOdEugkFUCwxzDiFgLM0jJHf471XuA5NfdpQCHztvNXOaWpKI4cdQnlqoEzU3VLXZmX2tobKKO93YjM4tc%2FFcK9dELs8Pa2ni6m1Oxk2k9pvL4I0r91V0x3SVoT2hHAGS7xE3MU&name=3WbtmkQwuJD1ArwLpmkJ8Eq8Yu47SdwPdkVaVYSwPJnOR%2BOOstCZnEeO8ormqiMxR9UNxYzAXoVbdwBP%2FRScnPJ7zGgw%2Bd8Vtc%2FNIonyb46aaO2jXno4xkr4LnSU3%2BZh"
          ]
        }
      ]
    },
    {
      "mgdbId": "",
      "pID": "3bbf9e24fcedbe13",
      "title": "豫光金铅女篮vs大连文体旅",
      "keyword": "11月26日14:30",
      "sportItemId": "2",
      "matchStatus": "1",
      "matchField": "",
      "competitionName": "WCBA季前赛B组",
      "padImg": "http://catvod.hxfrock.ggff.net/腾讯体育.png",
      "competitionLogo": "",
      "pkInfoTitle": "豫光金铅女篮vs大连文体旅",
      "modifyTitle": "WCBA季前赛B组 豫光金铅女篮vs大连文体旅",
      "presenters": "",
      "matchInfo": {
        "time": "11月26日14:30"
      },
      "nodes": [
        {
          "name": "豫光金铅女篮vs大连文体旅",
          "urls": [
            "https://mgev.188766.xyz/play?migutoken=d5e24ee572a8a01e8782c9ce62acf8fd&id=O%2F2cFg4tWRKUqa5MqKYpghyQb9dzP8QjqIp%2BFLrppHHEvdXpxJ%2BZibKqSjqLx27z7nl%2F%2BMJ2kRvzw4uRxvMJ6rVETd4ZptjAOglcHrU5llELU8j7PQVbbB79%2FNlt3jhSyeEEOgW7Vit2bR8uZV5uM0gIR2cd4DldaBhl10wWQrmQRhEezCXdzqrIG%2BO8YW4ZwLj4ZHUx%2BrEW5xfB6kxM81DnUbSmIYtqqITCaOKglRMGN7AK%2FeTDrmiMQsBcF2OjJ%2FISwB3xWHnzFdwGZG9qcABZXCUvRZi7zUkBQAfzl8Cjal3%2BoW9mPfzsv6HpsuB3&name=vCGahHssmFmp2FULAg%2F3BeVeg9mVMByKCODvUkjs7J2W8tzqaQfSa7TwaWYm9B%2F8uGvXIFdp5Zd9st3gyfZuUtV%2BsRuBQ8SvUzHUjdPFoQAyZcqEk6orMeeOUMoP5Jre"
          ]
        }
      ]
    },
    {
      "mgdbId": "",
      "pID": "16bd6ea3bb0267b4",
      "title": "NBA常规赛精彩回顾：老鹰vs奇才",
      "keyword": "11月26日16:00",
      "sportItemId": "2",
      "matchStatus": "0",
      "matchField": "",
      "competitionName": "NBA经典赛",
      "padImg": "http://catvod.hxfrock.ggff.net/腾讯体育.png",
      "competitionLogo": "",
      "pkInfoTitle": "NBA常规赛精彩回顾：老鹰vs奇才",
      "modifyTitle": "NBA经典赛 NBA常规赛精彩回顾：老鹰vs奇才",
      "presenters": "",
      "matchInfo": {
        "time": "11月26日16:00"
      },
      "nodes": [
        {
          "name": "NBA常规赛精彩回顾：老鹰vs奇才",
          "urls": [
            "https://mgev.188766.xyz/play?migutoken=8d1c110cd863f8c72c6d2a6302632d69&id=3eoRht0%2B%2BZLgleZ96GcelPLZ%2B%2BLktLSEGj%2BKoFKJAyeZbBWDpNfRaYzy9%2F4BDhwBO0PU%2FkQuKuxk9U06D386gs5EJaEgqp8CC6%2FKbrdHRdQGXIimfJ%2F5TT1XlX3xnHVD%2BAFrqJ0fEKZ%2FwXH5iwsgwdi91W7w%2B4sejEn%2BUnvj1ZnKiDzS5qwCWK2dq13hq4ZzMNXkT1tlRYpBMNJYVlF7eBYXkOXrG69XrvFjW707POFnETKYqUQL4eEA%2BIUvM5qKsjFA6Ytxe2WjwrqM0Df7L7RljK27tn%2FWOUZ6asBHwryet0Q5JkeTc%2Fm3GEan1Fxm&name=Q1VBL%2FnoA2bYbdqd9LHJ4proeLDnZ20Vka4Ydv4XY1XdcsKjQsH%2Fs8PgnY6%2FSMx%2BWB6u1iG%2Be3g4NXmqh%2Be%2B7tkiYC5R2iv2QUVrmR1z%2Fc%2FzrM3DKfgXAMzwBMvaZ%2B4g"
          ]
        }
      ]
    },
    {
      "mgdbId": "",
      "pID": "99d42e2109df664d",
      "title": "东莞新彤盛vs江苏南钢",
      "keyword": "11月26日17:00",
      "sportItemId": "2",
      "matchStatus": "0",
      "matchField": "",
      "competitionName": "WCBA季前赛A组",
      "padImg": "http://catvod.hxfrock.ggff.net/腾讯体育.png",
      "competitionLogo": "",
      "pkInfoTitle": "东莞新彤盛vs江苏南钢",
      "modifyTitle": "WCBA季前赛A组 东莞新彤盛vs江苏南钢",
      "presenters": "",
      "matchInfo": {
        "time": "11月26日17:00"
      },
      "nodes": [
        {
          "name": "东莞新彤盛vs江苏南钢",
          "urls": [
            "https://mgev.188766.xyz/play?migutoken=566efdacf53703ed0df9da3cfed939a5&id=sYuQAE8RGnF6jFOn7hVwrUmAqI9TqBuLyudtzuGDLRl4zbLsvqhpIW7YFSnOrIU0FsgOf7TDDC5tc5knMiqKRF57xw7OJSjrH7Ws1jxvfuRwhX%2BeLyGtrrFok6XvGP%2FTz3PZwjLF66gLc5J5J%2BtxZLwqYNl2zxrrVatLxlXTbMoI9epmxWaH5cei%2BkOuXxneDGJ9DTNoSiWED%2FmlUG1Ae4ZFv93zJkjrzCrYfL%2FXDq%2FF4jHGON5pDqs%2FfzhBzopjCEu%2F449lxDR6SCHl4MwTFuDLHqjYTebDrE9%2Fq7gf81sahLSGAKLr3OciDumzkdS9&name=LqcVkUe7xFF32PYL2s1Pzh1%2Fax03l4t7pAF7Ycjc9NtvKn3sNdvbYuvReucvUCqTRG67bMtvcDJRxHyRJVCCy1611mdU7MxSvG3YL71E4M0%3D"
          ]
        }
      ]
    },
    {
      "mgdbId": "",
      "pID": "686682ab5ba6c644",
      "title": "山西竹叶青酒vs上海浦发银行",
      "keyword": "11月26日17:00",
      "sportItemId": "2",
      "matchStatus": "0",
      "matchField": "",
      "competitionName": "WCBA季前赛A组",
      "padImg": "http://catvod.hxfrock.ggff.net/腾讯体育.png",
      "competitionLogo": "",
      "pkInfoTitle": "山西竹叶青酒vs上海浦发银行",
      "modifyTitle": "WCBA季前赛A组 山西竹叶青酒vs上海浦发银行",
      "presenters": "",
      "matchInfo": {
        "time": "11月26日17:00"
      },
      "nodes": [
        {
          "name": "山西竹叶青酒vs上海浦发银行",
          "urls": [
            "https://mgev.188766.xyz/play?migutoken=b4e855bc226979d6d181039dabee262f&id=1LyWaa9pPmXgzXgM2Qg7Fgit%2FJoyjIvIZ2bQm1EVKtfQagslmIZRhYVwHqHDgnrUqwqsEmYhOnOP%2BIm1ALzYTPxnh1STRM0ULimNyeZzH%2FJvTnHGiL1BSsuK3XMkLZn0UHIg4Ow7PsOmiZnIyaGf0qBsxCDWhAkVBLueViWHZf7CwhtoliBp09Xvu15Z%2BB6eNqJ9%2FJlSrHiHw64dbIxVWQGcYrbYYgnwonwxStC1GBj0jI05dVF7epE9vb1dnDg8E0sVUCIIz6x7NFtCCI98mB8Yfa8Ez5Pv1bpb1XqVQTXf%2BhdTQaybJKiHlVZnVJhy&name=DcYPpDnbBQuCzER8wXSwrZrUUUQmSV5AdYjNcTx%2Bz2GRqncj02Oh0HOSbHmEQ0UN1t35yu74SuXZOiCEUacub6NXxz3uJzpbOMB8xv6ji3KqwTLRqIGKi%2FmPDvwDgAP0"
          ]
        }
      ]
    },
    {
      "mgdbId": "",
      "pID": "426b905345d7a959",
      "title": "NBA常规赛精彩回顾：快船vs湖人",
      "keyword": "11月26日18:00",
      "sportItemId": "2",
      "matchStatus": "0",
      "matchField": "",
      "competitionName": "NBA经典赛",
      "padImg": "http://catvod.hxfrock.ggff.net/腾讯体育.png",
      "competitionLogo": "",
      "pkInfoTitle": "NBA常规赛精彩回顾：快船vs湖人",
      "modifyTitle": "NBA经典赛 NBA常规赛精彩回顾：快船vs湖人",
      "presenters": "",
      "matchInfo": {
        "time": "11月26日18:00"
      },
      "nodes": [
        {
          "name": "NBA常规赛精彩回顾：快船vs湖人",
          "urls": [
            "https://mgev.188766.xyz/play?migutoken=b3016b736e035d8caeb1c955ff6249f6&id=KMH7lDDL6FGHpBtpBBKIbICqV1tQVtXJi%2BXDsFi51BfGTzuBjUnhAwre9Ns8HP5LwIeAKUF3I9PDpeS7NontgWIsfJy2KIaID9eTAv3ZPGIq3HFNOk7K2NUcKfxkVFxdXNfZnjECvP82zR%2FHMuEOCF9LbvCeQPAm8IU3prE7G3A2lhnXooG64ymCEDg8UCAapqEG9rn9KY3EKaOL5SEBgLJFnp7KEew3EJy7wuTJFMBvhh9lLtVbEDmZlyblODECtPXJ%2FCqXnZN8eARcT%2Fkji4SLA1mPvBUSGgOcSfzIq01S0CW%2FgDPUllGWQQKnJyBX&name=JEUOvec4myQGxBSBn9o%2BwVqca16UpLKX6ctGsJK2fJWkWTICXTBCSJwzCy3LQ4cZ0kIIlGfxnjBBS%2B0Q%2BRpZaCWQK87z2euOz1iaILmz9osgq6mb892xE%2FBQilJnBIqO"
          ]
        }
      ]
    },
    {
      "mgdbId": "",
      "pID": "7e73ec4b27a4d5ab",
      "title": "石家庄英励vs武汉盛帆黄鹤",
      "keyword": "11月26日19:30",
      "sportItemId": "2",
      "matchStatus": "0",
      "matchField": "",
      "competitionName": "WCBA季前赛A组",
      "padImg": "http://catvod.hxfrock.ggff.net/腾讯体育.png",
      "competitionLogo": "",
      "pkInfoTitle": "石家庄英励vs武汉盛帆黄鹤",
      "modifyTitle": "WCBA季前赛A组 石家庄英励vs武汉盛帆黄鹤",
      "presenters": "",
      "matchInfo": {
        "time": "11月26日19:30"
      },
      "nodes": [
        {
          "name": "石家庄英励vs武汉盛帆黄鹤",
          "urls": [
            "https://mgev.188766.xyz/play?migutoken=e0e60c1cf4acb8c70be16e449fe723dd&id=vMlaSrJqluvs20XxfHHbUsl3yte6eCEBv0G8lp7fAazN%2BeKnSgEXnGqb0d3WwD3B8ZUkYE1hTHr9yBOnlnl%2BpJpGSGB7eOrI%2BkN3grUdNwKAL1wfK0eWsNWK4wTGXWx04ra8K4ouGMYRIcI1Q5qLsfTPMqJYxHcCuIjoM6jp5ShPdEdQUpkz6PmxuzSkgNUuwo7sF8g7R8gjBSQa%2BoPPoOITXPGrk0g5lKa5wNyWXVy5z5uSwW7qk5BQLNIsgsQJci4%2BNixRXHaHwwhaU6%2BsHeeRwF6wFeQ0NvTvL%2BliLMAA0s8kZyUCAIK6CQPzWKcb&name=skqelPgCFcygLiyIk1TRMXkfQ6PHrb4gxTgm%2Fr2IuBvE9j39XUl0ah7Fb2XmUfMPgNuEBOsuZDry1NdNsmTYV3vxK1Dl7%2BD7vmMk9UO3VPV2tvEsNmkDlLG0cDhauTBi"
          ]
        }
      ]
    },
    {
      "mgdbId": "",
      "pID": "ce58f21945b753c6",
      "title": "四川蜀道远达vs山东赤水河酒",
      "keyword": "11月26日19:30",
      "sportItemId": "2",
      "matchStatus": "0",
      "matchField": "",
      "competitionName": "WCBA季前赛A组",
      "padImg": "http://catvod.hxfrock.ggff.net/腾讯体育.png",
      "competitionLogo": "",
      "pkInfoTitle": "四川蜀道远达vs山东赤水河酒",
      "modifyTitle": "WCBA季前赛A组 四川蜀道远达vs山东赤水河酒",
      "presenters": "",
      "matchInfo": {
        "time": "11月26日19:30"
      },
      "nodes": [
        {
          "name": "四川蜀道远达vs山东赤水河酒",
          "urls": [
            "https://mgev.188766.xyz/play?migutoken=374233e88c5064543b367a4f59c06400&id=U1BV%2BghE8BspPhfXhrnnS%2Bhy4rUcT7Z2Jqz6sfjzS3vZTHWeO8JctJ%2BIs3sATu5RC4wTxQLeae5ZOjeJMuixj1QHpC45ZvVQKNWsdhSFRtAN1704x4jGNRfYFurpHoX4Z0VYs5JbunKfJbMi04jP7sX83dMLeA9yWxXoSTM0zupEh1t1D%2FIIY%2BwhiRGAF%2FgsFgE8syYlcLS0F%2FweqA4qnCKs8yBBrpNogA2kXKwpOOvFEvc8zCowQHrTsfFcJU7sCr6fYXtEtzyxlQgq4EXn2Wm9tjMxnWKez0ihRiHxVx9vNbawQOa2BZ9fEw5yRRd%2F&name=b9rNP6qfU7gpmkohvAq%2FBwPlie4wSTAz%2FLFWEKT9lGE4AoowNbk5mVnZLnBSLWbKvLzVcGnRdNqxmP8VTuVmblHIuzP%2FDjNOdNiWK9kjgb9AArJpdqncrgLoZfuiHNST"
          ]
        }
      ]
    },
    {
      "mgdbId": "",
      "pID": "f15e21334229b89d",
      "title": "NBA常规赛精彩回顾：快船vs湖人",
      "keyword": "11月26日20:00",
      "sportItemId": "2",
      "matchStatus": "0",
      "matchField": "",
      "competitionName": "NBA经典赛",
      "padImg": "http://catvod.hxfrock.ggff.net/腾讯体育.png",
      "competitionLogo": "",
      "pkInfoTitle": "NBA常规赛精彩回顾：快船vs湖人",
      "modifyTitle": "NBA经典赛 NBA常规赛精彩回顾：快船vs湖人",
      "presenters": "",
      "matchInfo": {
        "time": "11月26日20:00"
      },
      "nodes": [
        {
          "name": "NBA常规赛精彩回顾：快船vs湖人",
          "urls": [
            "https://mgev.188766.xyz/play?migutoken=c1940b57e9b049ab8c33f4565c945e35&id=fIDVWpkx5Riedijyx%2Fd06lBXJg36V0lT9YSU8dBtHqx8DgpSjAdcvf0W1Zehi%2FgfBvxL4eKsM1VQxJEEElCktSQcejPccVPuS2RlLJ6C%2BOozwVTMYCgG0VDsi1bKfElKeC8ZsPrpH2EipWIHfHiaf4puOH9M4QFeRb8yeQVhliCQCb64%2FK4J%2B7Fye7jEYNetNkOHhS%2BYBLNtcJ71xdfFpNBCIG5wEmTURn2h58nr%2B148lkgpng13BcB5z2lV%2F3BGwHUfwmXDeagdotUNp38UWg4dQ%2BKX3A6i6mMwkpvh5NrSkfen1M3VW3bX5OEpq9Up&name=QDid3oqIr6Nle5%2B%2FGwGXSOAvKdMDSNgPbCHR5xJg9KjlaqlE0n4W7HeNaU1MXOytyxHsuEHB%2BANX5P%2BgBq3xTo3f48s%2FgBvZ42ymyMBgKH48k7QjClpbhXWcmKv%2BKDHt"
          ]
        }
      ]
    }
  ],
  "timestamp": "2025-11-26T07:30:27.065Z",
  "shanghaiTime": "2025-11-26T15:30:27.065Z",
  "count": 25,
  "mode": "today",
  "source": "real"
}