{
  "success": true,
  "data": [
    {
      "mgdbId": "23584",
      "pID": "23584",
      "title": "Tigers.TV",
      "keyword": "06月23日00:00",
      "sportItemId": "8",
      "matchStatus": "1",
      "matchField": "",
      "competitionName": "Tigers.TV",
      "padImg": "",
      "competitionLogo": "https://api.ppv.to/assets/thumb/214e71b6918ed7e995fcb66b6cded21d-thumbnail.jpg",
      "pkInfoTitle": "New York Yankees vs. Detroit Tigers",
      "modifyTitle": "Tigers.TV",
      "presenters": "",
      "matchInfo": {
        "time": "06月23日00:00"
      },
      "nodes": [
        {
          "pID": "https://ppv.hxfkof.dpdns.org/?id=mlb%2F2026-06-22%2Fnyy-det",
          "name": "New York Yankees vs. Detroit Tigers"
        }
      ]
    },
    {
      "mgdbId": "23585",
      "pID": "23585",
      "title": "Rays.TV",
      "keyword": "06月23日00:00",
      "sportItemId": "8",
      "matchStatus": "1",
      "matchField": "",
      "competitionName": "Rays.TV",
      "padImg": "",
      "competitionLogo": "https://api.ppv.to/assets/thumb/fda72535ed1fa2cf4e8ac894d6a97bb8-thumbnail.jpg",
      "pkInfoTitle": "Kansas City Royals vs. Tampa Bay Rays",
      "modifyTitle": "Rays.TV",
      "presenters": "",
      "matchInfo": {
        "time": "06月23日00:00"
      },
      "nodes": [
        {
          "pID": "https://ppv.hxfkof.dpdns.org/?id=mlb%2F2026-06-22%2Fkc-tb",
          "name": "Kansas City Royals vs. Tampa Bay Rays"
        }
      ]
    },
    {
      "mgdbId": "23586",
      "pID": "23586",
      "title": "Marlins.TV",
      "keyword": "06月23日00:00",
      "sportItemId": "8",
      "matchStatus": "1",
      "matchField": "",
      "competitionName": "Marlins.TV",
      "padImg": "",
      "competitionLogo": "https://api.ppv.to/assets/thumb/8bc1028c808db5ef1a1e9b9c2fadcbd3-thumbnail.jpg",
      "pkInfoTitle": "Texas Rangers vs. Miami Marlins",
      "modifyTitle": "Marlins.TV",
      "presenters": "",
      "matchInfo": {
        "time": "06月23日00:00"
      },
      "nodes": [
        {
          "pID": "https://ppv.hxfkof.dpdns.org/?id=mlb%2F2026-06-22%2Ftex-mia",
          "name": "Texas Rangers vs. Miami Marlins"
        }
      ]
    },
    {
      "mgdbId": "23587",
      "pID": "23587",
      "title": "Nationals.TV",
      "keyword": "06月23日00:00",
      "sportItemId": "8",
      "matchStatus": "1",
      "matchField": "",
      "competitionName": "Nationals.TV",
      "padImg": "",
      "competitionLogo": "https://api.ppv.to/assets/thumb/2f870797b9d668169b53f482ae5c6030-thumbnail.jpg",
      "pkInfoTitle": "Philadelphia Phillies vs. Washington Nationals",
      "modifyTitle": "Nationals.TV",
      "presenters": "",
      "matchInfo": {
        "time": "06月23日00:00"
      },
      "nodes": [
        {
          "pID": "https://ppv.hxfkof.dpdns.org/?id=mlb%2F2026-06-22%2Fphi-wsh",
          "name": "Philadelphia Phillies vs. Washington Nationals"
        }
      ]
    },
    {
      "mgdbId": "23580",
      "pID": "23580",
      "title": "NBC Sports BO",
      "keyword": "06月23日00:00",
      "sportItemId": "2",
      "matchStatus": "1",
      "matchField": "",
      "competitionName": "NBC Sports BO",
      "padImg": "",
      "competitionLogo": "https://api.ppv.to/assets/thumb/64f04cbd4685bf040d7f62fd04c40722-thumbnail.jpg",
      "pkInfoTitle": "Chicago Sky vs. Connecticut Sun",
      "modifyTitle": "NBC Sports BO",
      "presenters": "",
      "matchInfo": {
        "time": "06月23日00:00"
      },
      "nodes": [
        {
          "pID": "https://ppv.hxfkof.dpdns.org/?id=wnba%2F2026-06-22%2Fchi-con",
          "name": "Chicago Sky vs. Connecticut Sun"
        }
      ]
    },
    {
      "mgdbId": "23588",
      "pID": "23588",
      "title": "Space City Home Network",
      "keyword": "06月23日00:00",
      "sportItemId": "8",
      "matchStatus": "1",
      "matchField": "",
      "competitionName": "Space City Home Network",
      "padImg": "",
      "competitionLogo": "https://api.ppv.to/assets/thumb/21cdd8d878e2cc2761d56b4a07a46da3-thumbnail.jpg",
      "pkInfoTitle": "Houston Astros vs. Toronto Blue Jays",
      "modifyTitle": "Space City Home Network",
      "presenters": "",
      "matchInfo": {
        "time": "06月23日00:00"
      },
      "nodes": [
        {
          "pID": "https://ppv.hxfkof.dpdns.org/?id=mlb%2F2026-06-22%2Fhou-tor",
          "name": "Houston Astros vs. Toronto Blue Jays"
        }
      ]
    },
    {
      "mgdbId": "23589",
      "pID": "23589",
      "title": "SNY",
      "keyword": "06月23日00:00",
      "sportItemId": "8",
      "matchStatus": "1",
      "matchField": "",
      "competitionName": "SNY",
      "padImg": "",
      "competitionLogo": "https://api.ppv.to/assets/thumb/ce1598f7c03f46b086999e6a6f057def-thumbnail.jpg",
      "pkInfoTitle": "Chicago Cubs vs. New York Mets",
      "modifyTitle": "SNY",
      "presenters": "",
      "matchInfo": {
        "time": "06月23日00:00"
      },
      "nodes": [
        {
          "pID": "https://ppv.hxfkof.dpdns.org/?id=mlb%2F2026-06-22%2Fchc-nym",
          "name": "Chicago Cubs vs. New York Mets"
        }
      ]
    },
    {
      "mgdbId": "23590",
      "pID": "23590",
      "title": "Reds.TV",
      "keyword": "06月23日00:00",
      "sportItemId": "8",
      "matchStatus": "1",
      "matchField": "",
      "competitionName": "Reds.TV",
      "padImg": "",
      "competitionLogo": "https://api.ppv.to/assets/thumb/b050a693b257514184ece1a12e68cce6-thumbnail.jpg",
      "pkInfoTitle": "Milwaukee Brewers vs. Cincinnati Reds",
      "modifyTitle": "Reds.TV",
      "presenters": "",
      "matchInfo": {
        "time": "06月23日00:00"
      },
      "nodes": [
        {
          "pID": "https://ppv.hxfkof.dpdns.org/?id=mlb%2F2026-06-22%2Fmil-cin",
          "name": "Milwaukee Brewers vs. Cincinnati Reds"
        }
      ]
    },
    {
      "mgdbId": "23581",
      "pID": "23581",
      "title": "Atlanta News First",
      "keyword": "06月23日00:00",
      "sportItemId": "2",
      "matchStatus": "1",
      "matchField": "",
      "competitionName": "Atlanta News First",
      "padImg": "",
      "competitionLogo": "https://api.ppv.to/assets/thumb/5a5cd4a851b3dd7465e36348037db55e-thumbnail.jpg",
      "pkInfoTitle": "Toronto Tempo vs. Atlanta Dream",
      "modifyTitle": "Atlanta News First",
      "presenters": "",
      "matchInfo": {
        "time": "06月23日00:00"
      },
      "nodes": [
        {
          "pID": "https://ppv.hxfkof.dpdns.org/?id=wnba%2F2026-06-22%2Ftor-atl",
          "name": "Toronto Tempo vs. Atlanta Dream"
        }
      ]
    },
    {
      "mgdbId": "23591",
      "pID": "23591",
      "title": "CHSN",
      "keyword": "06月23日00:00",
      "sportItemId": "8",
      "matchStatus": "1",
      "matchField": "",
      "competitionName": "CHSN",
      "padImg": "",
      "competitionLogo": "https://api.ppv.to/assets/thumb/7ebea8210dbfabd258b377d08738fde1-thumbnail.jpg",
      "pkInfoTitle": "Cleveland Guardians vs. Chicago White Sox",
      "modifyTitle": "CHSN",
      "presenters": "",
      "matchInfo": {
        "time": "06月23日00:00"
      },
      "nodes": [
        {
          "pID": "https://ppv.hxfkof.dpdns.org/?id=mlb%2F2026-06-22%2Fcle-chw",
          "name": "Cleveland Guardians vs. Chicago White Sox"
        }
      ]
    },
    {
      "mgdbId": "23592",
      "pID": "23592",
      "title": "Twins.TV",
      "keyword": "06月23日00:00",
      "sportItemId": "8",
      "matchStatus": "1",
      "matchField": "",
      "competitionName": "Twins.TV",
      "padImg": "",
      "competitionLogo": "https://api.ppv.to/assets/thumb/287312a08774a059d811080a426e96c1-thumbnail.jpg",
      "pkInfoTitle": "Los Angeles Dodgers vs. Minnesota Twins",
      "modifyTitle": "Twins.TV",
      "presenters": "",
      "matchInfo": {
        "time": "06月23日00:00"
      },
      "nodes": [
        {
          "pID": "https://ppv.hxfkof.dpdns.org/?id=mlb%2F2026-06-22%2Flad-min",
          "name": "Los Angeles Dodgers vs. Minnesota Twins"
        }
      ]
    },
    {
      "mgdbId": "23593",
      "pID": "23593",
      "title": "Cardinals.TV",
      "keyword": "06月23日00:00",
      "sportItemId": "8",
      "matchStatus": "1",
      "matchField": "",
      "competitionName": "Cardinals.TV",
      "padImg": "",
      "competitionLogo": "https://api.ppv.to/assets/thumb/befc90bc75e31b7a6c1d0cad6d4fcc88-thumbnail.jpg",
      "pkInfoTitle": "Arizona Diamondbacks vs. St. Louis Cardinals",
      "modifyTitle": "Cardinals.TV",
      "presenters": "",
      "matchInfo": {
        "time": "06月23日00:00"
      },
      "nodes": [
        {
          "pID": "https://ppv.hxfkof.dpdns.org/?id=mlb%2F2026-06-22%2Fari-stl",
          "name": "Arizona Diamondbacks vs. St. Louis Cardinals"
        }
      ]
    },
    {
      "mgdbId": "23582",
      "pID": "23582",
      "title": "USA Net",
      "keyword": "06月23日00:00",
      "sportItemId": "2",
      "matchStatus": "1",
      "matchField": "",
      "competitionName": "USA Net",
      "padImg": "",
      "competitionLogo": "https://api.ppv.to/assets/thumb/d05cabb29c6d37cac9502c6885af50fe-thumbnail.jpg",
      "pkInfoTitle": "Phoenix Mercury vs. Indiana Fever",
      "modifyTitle": "USA Net",
      "presenters": "",
      "matchInfo": {
        "time": "06月23日00:00"
      },
      "nodes": [
        {
          "pID": "https://ppv.hxfkof.dpdns.org/?id=wnba%2F2026-06-22%2Fphx-ind",
          "name": "Phoenix Mercury vs. Indiana Fever"
        }
      ]
    },
    {
      "mgdbId": "23492",
      "pID": "23492",
      "title": "FIFA World Cup",
      "keyword": "06月23日00:00",
      "sportItemId": "1",
      "matchStatus": "1",
      "matchField": "",
      "competitionName": "FIFA World Cup",
      "padImg": "",
      "competitionLogo": "https://api.ppv.to/assets/thumb/6bf8122b702d798ba31186e6619c89e4-thumbnail.jpg",
      "pkInfoTitle": "Norway vs. Senegal",
      "modifyTitle": "FIFA World Cup",
      "presenters": "",
      "matchInfo": {
        "time": "06月23日00:00"
      },
      "nodes": [
        {
          "pID": "https://ppv.hxfkof.dpdns.org/?id=wc%2F2026-06-22%2Fnor-sen",
          "name": "Norway vs. Senegal"
        }
      ]
    },
    {
      "mgdbId": "23594",
      "pID": "23594",
      "title": "Rockies.TV",
      "keyword": "06月23日00:40",
      "sportItemId": "8",
      "matchStatus": "1",
      "matchField": "",
      "competitionName": "Rockies.TV",
      "padImg": "",
      "competitionLogo": "https://api.ppv.to/assets/thumb/4873f0911f944515ab540d25ede0c505-thumbnail.jpg",
      "pkInfoTitle": "Boston Red Sox vs. Colorado Rockies",
      "modifyTitle": "Rockies.TV",
      "presenters": "",
      "matchInfo": {
        "time": "06月23日00:40"
      },
      "nodes": [
        {
          "pID": "https://ppv.hxfkof.dpdns.org/?id=mlb%2F2026-06-22%2Fbos-col",
          "name": "Boston Red Sox vs. Colorado Rockies"
        }
      ]
    }
  ],
  "timestamp": "2026-06-23T01:00:49.488Z",
  "shanghaiTime": "2026-06-23T09:00:49.489Z",
  "count": 15,
  "mode": "today",
  "source": "no_data"
}