{
  "success": true,
  "data": [
    {
      "mgdbId": "",
      "pID": "7621060309223347000",
      "title": "CBA:北京vs浙江等6场比赛同播 88 - 75",
      "keyword": "03月25日19:35",
      "sportItemId": "2",
      "matchStatus": "2",
      "matchField": "",
      "competitionName": "抖音CBA联赛",
      "padImg": "https://p3-webcast-sign.douyinpic.com/tos-cn-i-cyp3xxotkf/11ea1a8f8fa2426cb0e80d5aab63730a~tplv-qz53dukwul-common-resize:375:221.image?lk3s=b426d2a4&x-expires=1777090519&x-signature=x1D1HebmoHH%2FjGT8t74wzBPfEvc%3D",
      "competitionLogo": "",
      "pkInfoTitle": "北京北汽 vs 浙江稠州金租",
      "modifyTitle": "",
      "presenters": "",
      "matchInfo": {
        "time": "03月25日19:35"
      },
      "nodes": [
        {
          "name": "CBA:北京vs浙江等6场比赛同播 88 - 75",
          "url": "https://v26-show.douyinvod.com/fed40677456d179046fd75825f6ca7ab/69c62ae7/video/tos/cn/tos-cn-v-5c21e9/o0FEVXgwqDIZmTLGg4lpE7BPAsADeQUmDfEEpt/?a=1938&ch=0&cr=0&dr=0&er=0&lr=default&cd=0%7C0%7C0%7C0&cv=1&br=3661&bt=3661&cs=0&ds=4&ft=9eUQ9bBOBBkq8ZmosfuqU_vjVQWw&mime_type=video_mp4&qs=0&rc=Nmg4ODgzOmc4NTU1ZztlOUBpanFwa2drb2R4OjMzNDxnM0AxMGM1YmFgNS0xM2MuYjAvYSM0YC0ucWduZy5hLS1kLTBzcw%3D%3D&btag=c0000e00038000&dy_q=1774498505&l=20260326121505B9587C17AFA81611909E"
        }
      ]
    },
    {
      "mgdbId": "",
      "pID": "7621035773358200000",
      "title": "新疆vs山东 82 - 102",
      "keyword": "03月25日20:00",
      "sportItemId": "2",
      "matchStatus": "2",
      "matchField": "",
      "competitionName": "抖音CBA联赛",
      "padImg": "https://p11-webcast-sign.douyinpic.com/tos-cn-i-cyp3xxotkf/f5ded16588c24cc2b12ebcaffcf576d1~tplv-qz53dukwul-common-resize:375:221.image?lk3s=b426d2a4&x-expires=1777090519&x-signature=wjT6%2BQ3WFKtFXOfTSvnI5s4YCKA%3D",
      "competitionLogo": "",
      "pkInfoTitle": "新疆伊力特 vs 山东高速",
      "modifyTitle": "",
      "presenters": "",
      "matchInfo": {
        "time": "03月25日20:00"
      },
      "nodes": [
        {
          "name": "新疆vs山东 82 - 102",
          "url": "https://v6-show.douyinvod.com/349d6fdc0b41f6da096c20f746553487/69c625d9/video/tos/cn/tos-cn-v-5c21e9/oYEfAhxgYETD6LdlTaVCLeGPCSq6AehnGZBIXI/?a=1938&ch=0&cr=0&dr=0&er=0&lr=default&cd=0%7C0%7C0%7C0&cv=1&br=3280&bt=3280&cs=0&ds=4&ft=9eUQ9bBOBBkq8ZmoZsuqU_vjVQWw&mime_type=video_mp4&qs=0&rc=M2ZkZzY1NzY5aTw6aTNpM0BpM2R3cTdrb2t4OjMzNDxnM0AuL182YzAyXzExLjJfLl8yYSMxb3BrcWdmZi5hLS1kLWFzcw%3D%3D&btag=c0000e00038000&dy_q=1774498461&l=2026032612142110DE73035A28963F4753"
        },
        {
          "name": "原声:新疆vs山东 82 - 102",
          "url": "https://v6-show.douyinvod.com/b40c63b50a3104492c55cde7f0d88947/69c6246e/video/tos/cn/tos-cn-v-5c21e9/osGQhtD4Z6GpghAAJLBxaFzfe3fGlkTHlBhVCB/?a=1938&ch=0&cr=0&dr=0&er=0&lr=default&cd=0%7C0%7C0%7C0&cv=1&br=3416&bt=3416&cs=0&ds=4&ft=9eUQ9bBOBBkq8ZmoufuqU_vjVQWw&mime_type=video_mp4&qs=0&rc=OzM2ZmY8aTQ5ODRpNjtoOEBpM3VtOTxrb2t4OjMzNDxnM0AtMDEvYzY1X2AxNmMvXzEtYSNyczAycWdeZi5hLS1kLWFzcw%3D%3D&btag=c0000e00038000&dy_q=1774498506&l=20260326121506D60F8F4CB4EAB850225B"
        }
      ]
    },
    {
      "mgdbId": "",
      "pID": "7621060309223544000",
      "title": "吉林vs辽宁 82 - 75",
      "keyword": "03月25日19:35",
      "sportItemId": "2",
      "matchStatus": "2",
      "matchField": "",
      "competitionName": "抖音CBA联赛",
      "padImg": "https://p3-webcast-sign.douyinpic.com/tos-cn-i-cyp3xxotkf/28b660f432694462bb77897ab3656a33~tplv-qz53dukwul-common-resize:375:221.image?lk3s=b426d2a4&x-expires=1777090519&x-signature=HqF7ilHuqInNTln%2BIMokob5FCRA%3D",
      "competitionLogo": "",
      "pkInfoTitle": "长白山恩都里 vs 辽宁本钢",
      "modifyTitle": "",
      "presenters": "",
      "matchInfo": {
        "time": "03月25日19:35"
      },
      "nodes": [
        {
          "name": "吉林vs辽宁 82 - 75",
          "url": "https://v6-show.douyinvod.com/374372f591d39df7be3d848b883455b9/69c62ab6/video/tos/cn/tos-cn-v-5c21e9/ooPwNIiE4lmSfBBkgsKVDygF0e8qEpAQ7gylLE/?a=1938&ch=0&cr=0&dr=0&er=0&lr=default&cd=0%7C0%7C0%7C0&cv=1&br=3480&bt=3480&cs=0&ds=4&ft=9eUQ9bBOBBkq8ZmoufuqU_vjVQWw&mime_type=video_mp4&qs=0&rc=O2dkaDhpMzZnM2loNTM1Z0BpMzdxZDNrb2t4OjMzNDxnM0AzNmAtY2IzXi0xXmFfLzRiYSNtNmhycWcvZi5hLS1kLWFzcw%3D%3D&btag=c0000e00038000&dy_q=1774498506&l=20260326121506D60F8F4CB4EAB850225B"
        },
        {
          "name": "原声:吉林vs辽宁 82 - 75",
          "url": "https://v6-show.douyinvod.com/2f7f50a85479ee22881adc571a4e1c5c/69c621b0/video/tos/cn/tos-cn-v-5c21e9/oQzHT9TsdIl2AJ2QfB9pD8G4g6D3GAQ5qfwQzL/?a=1938&ch=0&cr=0&dr=0&er=0&lr=default&cd=0%7C0%7C0%7C0&cv=1&br=3596&bt=3596&cs=0&ds=4&ft=9eUQ9bBOBBkq8ZmoufuqU_vjVQWw&mime_type=video_mp4&qs=0&rc=PDdmO2U1Nzw1ZzplaDNpN0BpanNnPDhrbzx4OjMzNDxnM0AvYGIwLWMuNjAxNWFiYF5jYSNyZzBzcWduZy5hLS1kLTBzcw%3D%3D&btag=c0000e00038000&dy_q=1774498506&l=20260326121506D60F8F4CB4EAB850225B"
        }
      ]
    },
    {
      "mgdbId": "",
      "pID": "7621061210482742000",
      "title": "山西vs上海 80 - 112",
      "keyword": "03月25日19:35",
      "sportItemId": "2",
      "matchStatus": "2",
      "matchField": "",
      "competitionName": "抖音CBA联赛",
      "padImg": "https://p11-webcast-sign.douyinpic.com/tos-cn-i-cyp3xxotkf/40156c2f24ef4d6685caa04ffdb860c6~tplv-qz53dukwul-common-resize:375:221.image?lk3s=b426d2a4&x-expires=1777090519&x-signature=L68XPJyw05ZYtsXfwbN1c5SoHp4%3D",
      "competitionLogo": "",
      "pkInfoTitle": "山西汾酒 vs 上海久事",
      "modifyTitle": "",
      "presenters": "",
      "matchInfo": {
        "time": "03月25日19:35"
      },
      "nodes": [
        {
          "name": "山西vs上海 80 - 112",
          "url": "https://v9-show.douyinvod.com/4ff4d5fb364cad91d04108c8f561c04d/69c62ab4/video/tos/cn/tos-cn-v-5c21e9/o4NSINIpo4DPCKE5YfejAlpgrQNgZBmwEyKqEs/?a=1938&ch=0&cr=0&dr=0&er=0&lr=default&cd=0%7C0%7C0%7C0&cv=1&br=3740&bt=3740&cs=0&ds=4&ft=9eUQ9bBOBBkq8ZmoAfuqU_vjVQWw&mime_type=video_mp4&qs=0&rc=aTRmZmRpZThlNjY4OGlkO0BpM3M7bDZrb254OjMzNDxnM0A1YjAvYGEzNTExYzQzLV4wYSMxbmpocWcvZi5hLS1kLWFzcw%3D%3D&btag=c0000e00038000&dy_q=1774498504&l=20260326121504B4930708EB3BC1852333"
        }
      ]
    },
    {
      "mgdbId": "",
      "pID": "7621066466682476000",
      "title": "广东vs四川 93 - 51",
      "keyword": "03月25日19:35",
      "sportItemId": "2",
      "matchStatus": "2",
      "matchField": "",
      "competitionName": "抖音CBA联赛",
      "padImg": "https://p3-webcast-sign.douyinpic.com/tos-cn-i-cyp3xxotkf/86bb9f6259464230bcfca2c24be7b094~tplv-qz53dukwul-common-resize:375:221.image?lk3s=b426d2a4&x-expires=1777090519&x-signature=pGFHcK9aFu8sB7VTWBQSLKeY%2BNc%3D",
      "competitionLogo": "",
      "pkInfoTitle": "广东东阳光 vs 四川丰谷酒业",
      "modifyTitle": "",
      "presenters": "",
      "matchInfo": {
        "time": "03月25日19:35"
      },
      "nodes": [
        {
          "name": "广东vs四川 93 - 51",
          "url": "https://v6-show.douyinvod.com/6655cff6deacd031c9c28cf1a5c74ccb/69c62ab6/video/tos/cn/tos-cn-v-5c21e9/okPHlfWapQNIQRAdfBw9M2SsJ54AVODwrgqn2m/?a=1938&ch=0&cr=0&dr=0&er=0&lr=default&cd=0%7C0%7C0%7C0&cv=1&br=3530&bt=3530&cs=0&ds=4&ft=9eUQ9bBOBBkq8ZmoufuqU_vjVQWw&mime_type=video_mp4&qs=0&rc=ZzY3O2gzNGRkNjM6ZThkNkBpajptZmhrb294OjMzNDxnM0BhNWBeMTViXi8xNjZeMS4uYSNpZG9pcWduZi5hLS1kLWFzcw%3D%3D&btag=c0000e00038000&dy_q=1774498506&l=20260326121506D60F8F4CB4EAB850225B"
        },
        {
          "name": "原声:广东vs四川 93 - 51",
          "url": "https://v6-show.douyinvod.com/ee014bd41de0ef8980b6ac3032b775cc/69c62331/video/tos/cn/tos-cn-v-5c21e9/oABjQIHslCuq9SWOegAfNJDwQDOpqG44Vi1A9B/?a=1938&ch=0&cr=0&dr=0&er=0&lr=default&cd=0%7C0%7C0%7C0&cv=1&br=4268&bt=4268&cs=0&ds=4&ft=9eUQ9bBOBBkq8ZmoufuqU_vjVQWw&mime_type=video_mp4&qs=0&rc=aTg2PDtkPGg6ZGQ1OztoM0BpamtvbzZrb2t4OjMzNDxnM0AvXjA2LWAxX2AxYF4tXjBjYSNncW4wcWdeZi5hLS1kLS9zcw%3D%3D&btag=c0000e00038000&dy_q=1774498506&l=20260326121506D60F8F4CB4EAB850225B"
        }
      ]
    },
    {
      "mgdbId": "",
      "pID": "7621057740857218000",
      "title": "原声:宁波vs福建 88 - 75",
      "keyword": "03月25日19:35",
      "sportItemId": "2",
      "matchStatus": "2",
      "matchField": "",
      "competitionName": "抖音CBA联赛",
      "padImg": "https://p3-webcast-sign.douyinpic.com/tos-cn-i-cyp3xxotkf/562988d4a3a74de5820f347d64e0833b~tplv-qz53dukwul-common-resize:375:221.image?lk3s=b426d2a4&x-expires=1777090519&x-signature=67095WcyPhcFKcZgfnBCfWaITvg%3D",
      "competitionLogo": "",
      "pkInfoTitle": "北京北汽 vs 浙江稠州金租",
      "modifyTitle": "",
      "presenters": "",
      "matchInfo": {
        "time": "03月25日19:35"
      },
      "nodes": [
        {
          "name": "原声:宁波vs福建 88 - 75",
          "url": "https://v6-show.douyinvod.com/88d54da50fb831a1494ccfdac11c72f4/69c6294b/video/tos/cn/tos-cn-v-5c21e9/okQHJABtLfShG4xTV6G7VupZelihHZIAEJeZCz/?a=1938&ch=0&cr=0&dr=0&er=0&lr=default&cd=0%7C0%7C0%7C0&cv=1&br=3853&bt=3853&cs=0&ds=4&ft=9eUQ9bBOBBkq8ZmoufuqU_vjVQWw&mime_type=video_mp4&qs=0&rc=Ojg7PGdoaDpmOzNmZGloOkBpanVsbztrb2t4OjMzNDxnM0AxYzIvYWNjNTYxYGEyY14vYSNrMWZmcWduZi5hLS1kLS9zcw%3D%3D&btag=c0000e00038000&dy_q=1774498506&l=20260326121506D60F8F4CB4EAB850225B"
        }
      ]
    },
    {
      "mgdbId": "",
      "pID": "983488708402",
      "title": "抖音CBA直播间",
      "keyword": "03月26日19:30",
      "sportItemId": "2",
      "matchStatus": "1",
      "matchField": "",
      "competitionName": "CBA联赛",
      "padImg": "http://catvod.957.de5.net/抖音CBA.png",
      "competitionLogo": "",
      "pkInfoTitle": "抖音CBA直播间",
      "modifyTitle": "",
      "presenters": "",
      "matchInfo": {
        "time": "03月26日19:30"
      },
      "nodes": [
        {
          "name": "抖音CBA直播 [非直播时间为CCTV13直播]",
          "url": "http://pull-flv-f26.douyincdn.com/media/stream-695505348295131820.flv?arch_hrchy=w1&exp_hrchy=w1&expire=69cded5c&major_anchor_level=common&sign=a4e7c8d0fb9f012e70abd8986f01d892&t_id=037-20260326121524271FB1D705C72C686411-kxgP3H&unique_id=stream-695505348295131820_684_flv"
        }
      ]
    }
  ],
  "timestamp": "2026-03-26T04:15:24.631Z",
  "shanghaiTime": "2026-03-26T12:15:24.631Z",
  "count": 7,
  "mode": "all",
  "source": "cba_live"
}