{
  "success": true,
  "data": [
    {
      "mgdbId": "",
      "pID": "983488708402",
      "title": "抖音CBA直播间",
      "keyword": "02月23日19:30",
      "sportItemId": "2",
      "matchStatus": "1",
      "matchField": "",
      "competitionName": "CBA联赛",
      "padImg": "http://catvod.957.de5.net/抖音CBA.png",
      "competitionLogo": "",
      "pkInfoTitle": "抖音CBA直播间",
      "modifyTitle": "",
      "presenters": "",
      "matchInfo": {
        "time": "02月23日19:30"
      },
      "nodes": [
        {
          "name": "抖音CBA直播 [非直播时间为CCTV13直播]",
          "urls": [
            "http://pull-flv-f26.douyincdn.com/media/stream-407136188858892972.flv?arch_hrchy=w1&exp_hrchy=w1&expire=69a55fbc&major_anchor_level=common&sign=1f030b2a2e44f1d9899703ae20a9e4e0&t_id=037-20260223180028F884297A2B5AE3754BAA-6sSA12&unique_id=stream-407136188858892972_684_flv"
          ]
        }
      ]
    }
  ],
  "timestamp": "2026-02-23T10:00:29.084Z",
  "shanghaiTime": "2026-02-23T18:00:29.084Z",
  "count": 1,
  "mode": "today",
  "source": "cba_live"
}