{
  "success": true,
  "data": [
    {
      "mgdbId": "",
      "pID": "983488708402",
      "title": "抖音CBA直播间",
      "keyword": "04月24日19:30",
      "sportItemId": "2",
      "matchStatus": "1",
      "matchField": "",
      "competitionName": "CBA联赛",
      "padImg": "http://catvod.957.de5.net/抖音CBA.png",
      "competitionLogo": "",
      "pkInfoTitle": "抖音CBA直播间",
      "modifyTitle": "",
      "presenters": "",
      "matchInfo": {
        "time": "04月24日19:30"
      },
      "nodes": [
        {
          "name": "抖音CBA直播 [非直播时间为CCTV13直播]",
          "url": "http://pull-flv-f11.douyincdn.com/media/stream-695673841736745644.flv?arch_hrchy=w1&exp_hrchy=w1&expire=1777586428&major_anchor_level=common&neq=1&sign=5326bb2465cea5b6d68a04bc0bcddf91&t_id=037-202604240600287B45BC8D8ACC979431C1-dsZr2s&unique_id=stream-695673841736745644_684_flv"
        }
      ]
    }
  ],
  "timestamp": "2026-04-23T22:00:28.847Z",
  "shanghaiTime": "2026-04-24T06:00:28.847Z",
  "count": 1,
  "mode": "today",
  "source": "cba_live"
}