{
  "success": true,
  "data": [
    {
      "mgdbId": "",
      "pID": "7642589866635089000",
      "title": "CBA季后赛:北京vs上海 85 - 99",
      "keyword": "05月22日19:35",
      "sportItemId": "2",
      "matchStatus": "2",
      "matchField": "",
      "competitionName": "抖音CBA联赛",
      "padImg": "https://p3-webcast-sign.douyinpic.com/tos-cn-i-cyp3xxotkf/84d5d88379884051ba958d496667ee02~tplv-qz53dukwul-common-resize:375:221.image?lk3s=b426d2a4&x-expires=1782076224&x-signature=vOiDNoEWVTzmc9uKw5y1sdtnvac%3D",
      "competitionLogo": "",
      "pkInfoTitle": "北京北汽 vs 上海久事",
      "modifyTitle": "",
      "presenters": "",
      "matchInfo": {
        "time": "05月22日19:35"
      },
      "nodes": [
        {
          "name": "CBA季后赛:北京vs上海 85 - 99",
          "url": "https://v26-show.douyinvod.com/abc2fbdef1e3f158e4f299f4b7d30b98/6a123c32/video/tos/cn/tos-cn-v-5c21e9/oITjgDPqFNAcNZSq4E6VABgAnfUf4og1lNxzQb/?a=1938&ch=0&cr=0&dr=0&er=0&lr=default&cd=0%7C0%7C0%7C0&cv=1&br=3143&bt=3143&cs=0&ds=4&ft=9eUQ9bBOBBkq8ZmorNe~k_vjVQWw&mime_type=video_mp4&qs=0&rc=ZjlnZjtnaTVnNDkzZjVkNkBpM3Nnb2Zrbzk4OzMzNDxnM0A2MzQ0YzNhXmIxYWIyMTEvYSNxNDNycWducDVhLS1kLWFzcw%3D%3D&btag=80000e00038000&dy_q=1779484218&l=20260523051017EA9FB652FC0BFDD06EB6"
        }
      ]
    },
    {
      "mgdbId": "",
      "pID": "7642226755117733000",
      "title": "CBA季后赛:深圳vs广厦 91 - 80",
      "keyword": "05月21日19:35",
      "sportItemId": "2",
      "matchStatus": "2",
      "matchField": "",
      "competitionName": "抖音CBA联赛",
      "padImg": "https://p3-webcast-sign.douyinpic.com/tos-cn-i-cyp3xxotkf/a9a6275a5e754a9dbca6cf6e36cdfec0~tplv-qz53dukwul-common-resize:375:221.image?lk3s=b426d2a4&x-expires=1782076229&x-signature=uDAWnj61k2qZIzCEEx8iMyVuZXU%3D",
      "competitionLogo": "",
      "pkInfoTitle": "深圳马可波罗 vs 浙江浙商证券",
      "modifyTitle": "",
      "presenters": "",
      "matchInfo": {
        "time": "05月21日19:35"
      },
      "nodes": [
        {
          "name": "CBA季后赛:深圳vs广厦 91 - 80",
          "url": "https://v9-show.douyinvod.com/f0ee894c56b9898fc233f07fbe31fbad/6a123c65/video/tos/cn/tos-cn-v-5c21e9/o8D8gqzn4AA192Fo0PsK4hI3BAhEPfAQSESaaB/?a=1938&ch=0&cr=0&dr=0&er=0&lr=default&cd=0%7C0%7C0%7C0&cv=1&br=3435&bt=3435&cs=0&ds=4&ft=9eUQ9bBOBBkq8ZmoXNe~k_vjVQWw&mime_type=video_mp4&qs=0&rc=aTdlNzs1aWU5NWVnNWk8NEBpanNkdjxrb3RqOzMzNDxnM0AxMzRjNjYwXzMxLS5eLi1gYSNzLXAwcWdebjRhLS1kLS9zcw%3D%3D&btag=c0000e00038000&dy_q=1779484219&l=202605230510198D2B5B1A56E67F9D8232"
        }
      ]
    },
    {
      "mgdbId": "",
      "pID": "7642610431307388000",
      "title": "原声:北京vs上海 85 - 99",
      "keyword": "05月22日19:35",
      "sportItemId": "2",
      "matchStatus": "2",
      "matchField": "",
      "competitionName": "抖音CBA联赛",
      "padImg": "https://p3-webcast-sign.douyinpic.com/tos-cn-i-cyp3xxotkf/177422738679435f85d6c4e82b220978~tplv-qz53dukwul-common-resize:375:221.image?lk3s=b426d2a4&x-expires=1782076224&x-signature=HMEW9bGp4SfSLDRCPhLNLwUnhDo%3D",
      "competitionLogo": "",
      "pkInfoTitle": "北京北汽 vs 上海久事",
      "modifyTitle": "",
      "presenters": "",
      "matchInfo": {
        "time": "05月22日19:35"
      },
      "nodes": [
        {
          "name": "原声:北京vs上海 85 - 99",
          "url": "https://v6-show.douyinvod.com/c799bcfaad3f702ce9b36e71c446b21e/6a123c2c/video/tos/cn/tos-cn-v-5c21e9/oAReQDQDI4D0emHFvF9JAlqAAQxg6BQEJaKJgs/?a=1938&ch=0&cr=0&dr=0&er=0&lr=default&cd=0%7C0%7C0%7C0&cv=1&br=3479&bt=3479&cs=0&ds=4&ft=9eUQ9bBOBBkq8Zmoj4e~k_vjVQWw&mime_type=video_mp4&qs=0&rc=ZjM3MzVmNzVlZmQ3aTZkNEBpM3dvdjdrbzc4OzMzNDxnM0AuLS41LzFfNi8xMl81LzJiYSMxZW1kcWcvcjVhLS1kLTBzcw%3D%3D&btag=80000e00038000&dy_q=1779484224&l=202605230510245C8B127EE12E09593E3F"
        }
      ]
    },
    {
      "mgdbId": "",
      "pID": "7642211019742156000",
      "title": "原声:深圳vs广厦 91 - 80",
      "keyword": "05月21日19:35",
      "sportItemId": "2",
      "matchStatus": "2",
      "matchField": "",
      "competitionName": "抖音CBA联赛",
      "padImg": "https://p11-webcast-sign.douyinpic.com/tos-cn-i-cyp3xxotkf/98d92a72211b4b01aa12d082fa81fbd8~tplv-qz53dukwul-common-resize:375:221.image?lk3s=b426d2a4&x-expires=1782076229&x-signature=0LDEwLzr7jQ%2B6UNKycK0bSAW7VE%3D",
      "competitionLogo": "",
      "pkInfoTitle": "深圳马可波罗 vs 浙江浙商证券",
      "modifyTitle": "",
      "presenters": "",
      "matchInfo": {
        "time": "05月21日19:35"
      },
      "nodes": [
        {
          "name": "原声:深圳vs广厦 91 - 80",
          "url": "https://v26-show.douyinvod.com/862ce2a2b855d86f2093ca8fa728bc13/6a123c3b/video/tos/cn/tos-cn-v-5c21e9/ogEAMAVZjgDeqa0DaSB2ldDwQ1gq6YQrxygwVe/?a=1938&ch=0&cr=0&dr=0&er=0&lr=default&cd=0%7C0%7C0%7C0&cv=1&br=3748&bt=3748&cs=0&ds=4&ft=9eUQ9bBOBBkq8ZmoC4e~k_vjVQWw&mime_type=video_mp4&qs=0&rc=NzNlaTwzZ2VpN2VnODg7ZEBpam1yZWZrbzlqOzMzNDxnM0A2MzUuLzU0XmExLzAyMy8zYSMzYl5ncWdmbzRhLS1kLTBzcw%3D%3D&btag=80000e00038000&dy_q=1779484229&l=20260523051028BD15718C66B21061DB31"
        }
      ]
    },
    {
      "mgdbId": "",
      "pID": "983488708402",
      "title": "抖音CBA直播间",
      "keyword": "05月23日19:30",
      "sportItemId": "2",
      "matchStatus": "1",
      "matchField": "",
      "competitionName": "CBA联赛",
      "padImg": "http://catvod.957.de5.net/抖音CBA.png",
      "competitionLogo": "",
      "pkInfoTitle": "抖音CBA直播间",
      "modifyTitle": "",
      "presenters": "",
      "matchInfo": {
        "time": "05月23日19:30"
      },
      "nodes": [
        {
          "name": "抖音CBA直播 [非直播时间为CCTV13直播]",
          "url": "http://pull-flv-f11.douyinliving.com/media/stream-695858260985774930.flv?expire=1780089031&sign=208e351591c846d69421b681cf5b9876&neq=1&s_anchor=1&arch_hrchy=s2&major_anchor_level=vip&unique_id=stream-695858260985774930_850_flv&t_id=037-20260523051031AC7161B1F16AC2244CAA-pGR3ya"
        }
      ]
    }
  ],
  "timestamp": "2026-05-22T21:10:31.927Z",
  "shanghaiTime": "2026-05-23T05:10:31.927Z",
  "count": 5,
  "mode": "all",
  "source": "cba_live"
}