{
  "success": true,
  "data": [
    {
      "mgdbId": "",
      "pID": "a5f4999a0c6ef7fb",
      "title": "尼克斯vs活塞",
      "keyword": "01月06日08:00",
      "sportItemId": "2",
      "matchStatus": "2",
      "matchField": "",
      "competitionName": "NBA常规赛",
      "padImg": "http://catvod.hxfrock.ggff.net/腾讯体育.png",
      "competitionLogo": "",
      "pkInfoTitle": "尼克斯vs活塞",
      "modifyTitle": "NBA常规赛 尼克斯vs活塞",
      "presenters": "",
      "matchInfo": {
        "time": "01月06日08:00"
      },
      "nodes": [
        {
          "name": "胡鹤明",
          "urls": [
            "https://mgev.188766.xyz/play?migutoken=0f9df59f76ca6922889b680548023684&id=MW8UFi5me%2Bdcom3gqZ%2Fgl463uSXiGU4p41btXQ6rJwbB53hEjwjybaE4RRPdTxkj4ACIncJ4Tb%2BUvxCNYXz234oRZ4Y1fW4j8mHeXHdJB0RGwOQjssDlYp0CUrFRg7YVZOEpXolsMka8KuPYjhfuM%2BWdGKTIcE1TqFNF6HjV1fVLXZhH8Xm2UA7uUE5X5APskeqrRQTUPGlN8fyo7tHMvu0gfcrdfIg9hVSALjiVWpb%2B9asmHSEuSjeSQvSoc0yChKfn%2BsWLPLpAnDrGE8mZYef9TbbOyYRbOt%2B3TaTgLkU%3D&name=IQuGd6ZWT%2Fu3rWHClZydsObYVQYqnEVIsazUIw7KqXnvEVbhrGh7sJVXB%2F92mr4MxiqGEsVyqK39A5%2BGsrsqhI4ELTSTMY%2FS8%2B69K491ZhM%3D"
          ]
        },
        {
          "name": "英文原音",
          "urls": [
            "https://mgev.188766.xyz/play?migutoken=63579df76e780ed3399ad90eaba882df&id=NUWoiKkn1%2BpTq8XqXUOwsxZymFgGHAQ%2BaRpImoP28%2FZ%2BPaOBmQ3Be18g3pYNbP74gMvojUJuqvh3L55EFCVNFOjaTTljbLaYkZu57KDtHpF8Gr6G8bg88Pw8Z4gduOUZyfozFMs4ap9qAmDnZrzMefbP6gmq7EclOFMrBKfS6CED1DiNeVKF9Goxn0VwHseC%2B6lhwqxG6N1Ph15Ezz9roUeZunm%2FDeQYZATZNELcbk14dU4J%2BLiOXF1TTSKFZ3KSuuRqdWkVW5LrsvuWLF4puEU%2FiAuSAO%2BnGQd6Br5XvB0%3D&name=tp1xs6dx573n8omyWdarVNhsY3W8IJrvhIpNPYTE4E%2B%2BP5YmFA%2FPgfoQYnElyVbFUq0c9WW%2FvjBfHqR%2FFwzvtJZ4vti7uGWthig62p%2FH6IA%3D"
          ]
        }
      ]
    },
    {
      "mgdbId": "",
      "pID": "e6d8b9156b236227",
      "title": "公牛vs凯尔特人",
      "keyword": "01月06日08:30",
      "sportItemId": "2",
      "matchStatus": "2",
      "matchField": "",
      "competitionName": "NBA常规赛",
      "padImg": "http://catvod.hxfrock.ggff.net/腾讯体育.png",
      "competitionLogo": "",
      "pkInfoTitle": "公牛vs凯尔特人",
      "modifyTitle": "NBA常规赛 公牛vs凯尔特人",
      "presenters": "",
      "matchInfo": {
        "time": "01月06日08:30"
      },
      "nodes": [
        {
          "name": "李雪儿",
          "urls": [
            "https://mgev.188766.xyz/play?migutoken=f974da80060c1161cfa49c0f6aa2e51f&id=f7jE9E45gsP9pxlu0E%2FSuibNeXtzjujIkMgL%2FBnn4TvPQZ6AT64VPIkefpx6j8aCBDWdgUQfU%2FOYiZvW%2FO7PeAjeJhDGP6WciuW%2BVKQb4rj5NXLb39sdlkTJgeK%2Bc9Jgif82D9KIOD1LFwMWG%2BriE7LEMuXU8Tjg%2BFBvXKT7gslKCzOlxPsnFjq2yWrd9PtzDUvpVFJHn6AsxnwQ7dtNR%2FBa0gwGzf3pfH0KVm56nf05CG29Jep0d6r%2B%2BpaV4qPXIKoSUbbVeUTIGopsP4YOO6dHB8jv4SIex501LF1%2F3vI%3D&name=0K3onpH0KIMgar%2Fwbeqk%2Bsk69SK5lTeXduAnLHIben%2Fptcf4FH15cHCe0axP4iReQGAjR%2FTYhWgmDCoUyfMlZUhiW%2B%2B22Ng%2B3gV%2B%2BhF7EDU%3D"
          ]
        },
        {
          "name": "英文原音",
          "urls": [
            "https://mgev.188766.xyz/play?migutoken=c2d1ffd85ba6aa055bb526e1f3ee48f8&id=ahrLd7zfGQ9CX9LvVqQNjUTlp9cTpBPb5wnS%2FjMjh%2FxFQg5RjysFbE0vbbsKRpUhOgp%2Bi1TmeIyg1jhJtgCm1w5mRUTzmh06jCcPGn0eMaNAnZd8F8qcWcXTxop6L8%2FwT3BM0T9140VpT52HoBBnr3BCsx7IKBX8j5wAVhvr%2BbSF2LxDuYCNX8KJzOcrW8pq0%2FCFYUVO4mKvYbO8YDCJ%2BNDJ5qlZ8s15s%2F2HKzk1kFEtleQ02htwbl5TZhbBe%2Fbpwwrp%2F4KEzlId2C%2Bm5UZFFkhNTP9lWy6mb73fZ3NO0S4%3D&name=IT10UoA29a45MlUEcgWZ0mwq2YojfL6qPMYFmiZgRZW%2FVEZk4s718P2PqoqTew%2BuDQiB88Rzq53%2BDOTKahnBSoiI7ITxjrBexeBsqoh%2F77M%3D"
          ]
        }
      ]
    },
    {
      "mgdbId": "",
      "pID": "22c762916b9c0d22",
      "title": "老鹰vs猛龙",
      "keyword": "01月06日08:30",
      "sportItemId": "2",
      "matchStatus": "2",
      "matchField": "",
      "competitionName": "NBA常规赛",
      "padImg": "http://catvod.hxfrock.ggff.net/腾讯体育.png",
      "competitionLogo": "",
      "pkInfoTitle": "老鹰vs猛龙",
      "modifyTitle": "NBA常规赛 老鹰vs猛龙",
      "presenters": "",
      "matchInfo": {
        "time": "01月06日08:30"
      },
      "nodes": [
        {
          "name": "石楷文",
          "urls": [
            "https://mgev.188766.xyz/play?migutoken=16bdbaff85f91d5b52da2aa62cbcc46a&id=ZY87rDCLB9rt3dGIGkciJtW5tYuxf4R%2FBeBDq6cdk50UpNSspmU8WLgFliZRicfnNa5JsjfdsP7yyTTXi3dwqtGU%2BQ1l8m%2FRsJ8edAeqWlZVWTp67YY0VEECcZ6bZZNtPizq5yTgnfjSIY5lH5mFQUHm49DBJytnxwtN8eWv68eB%2BJooi%2BXf7HuqyUnuwZCEPpDP4T%2BxVMDEh4UJY6X5TxahA%2B7f5%2FNWifN2CLqTnNMxV9RgW46%2FMtaHbT2r1yFroFA8vC1enOiJU2PTkicsmESAP0MbhLHC6abvYt0Xsvk%3D&name=IbNEKuPRFee5HR0ORPcBMCNw3bBObYbmyl%2Ben9WBCgbsUoEF66mokjXt2FPbhGUmWLq3AApLilHqUwodFrNcX%2BZw9QlUUdhZTGclHI4i8B8%3D"
          ]
        },
        {
          "name": "英文原音",
          "urls": [
            "https://mgev.188766.xyz/play?migutoken=6659dee5bfc84ccb6170bfe03a43e636&id=2%2Br1uJM69HIigu14J0quExdVPuVnhnt6q4TzLZXRvjBjECNf2iofOEtlQcBz5XazhoI2yL8zpej4ZWLXmVWA2Ht38V29bDezwfygOMBDSEEyXsbyuhOz35shXFSwvvk5Du6XMG9Y91%2FoLCmJLE0P%2BEnCT1kSJ%2BPixjZHIb5xpBAndPoWnA%2B%2BT16MWZUK49rDZkb83M%2BYGJHoZzVaWNpgOcI5sCTkU90Q4MWKY9B2xgl06jhFl5R6nnHPS6x0L9jm2iVN29FrY8QS4mMOI9qJoV18xr33ydDfcK4SCmM7VZc%3D&name=NetrYO2CtzKJOuB3Xp0huKH0hUtvhSE%2FG2Wm1bBCCRI%2BYlkR5umMM%2BFxW2zTgds5vnAUL8smK2WaMaOlMIEouOqWiLtdS2%2FcG2f31qkOVxw%3D"
          ]
        }
      ]
    },
    {
      "mgdbId": "",
      "pID": "9b52c62c6408f4bb",
      "title": "WTA500布里斯班站",
      "keyword": "01月06日09:00",
      "sportItemId": "3",
      "matchStatus": "2",
      "matchField": "",
      "competitionName": "WTA500布里斯班站",
      "padImg": "http://catvod.hxfrock.ggff.net/腾讯体育.png",
      "competitionLogo": "",
      "pkInfoTitle": "WTA500布里斯班站",
      "modifyTitle": "WTA500布里斯班站 WTA500布里斯班站",
      "presenters": "",
      "matchInfo": {
        "time": "01月06日09:00"
      },
      "nodes": [
        {
          "name": "第2轮 第1日",
          "urls": [
            "https://mgev.188766.xyz/play?migutoken=40994cb2c0ac55375c5c2651f5f1032b&id=adAZDlJ5khWhlhzyZuoVK%2BQpAMv1NxbsyEYRVU8Q42YhQ9pe5Ha5X65%2FaMFloKfujpemgvj9rWils3sXUp%2Bn83pv9Nh5rcLZe3h46Gt90wuLQFN9j1F3aCjusaLFzcheTZCAktEBWvzXXqF9OG4%2B4cLlqTWJjWl9zrnCFU24Se10RcXuD%2BXT7leqRJWUGWDQc9uVJDrLiNn%2FCqkXSbgVLj2Pvxn3ufVApEPtn7iTRbHShX1YQW5ep92TUi0pANSSB1USnr23EHHlrAYryIPjDW%2Bfzem1ZEzU5qzJ4rXftWCaR%2FnyNNZY80M8kk6QE28Y&name=ttOPm9A3VdTX%2FCkxpKXQiXkrnEXYi2LYnBGQry2Vwp7rba5AYiU1QWNKPCxU9vkDTy9f6d9V4b2f4AWrOrSUJHeWHxpSZrd4Akx%2BmxCNgBkALxu5XHnRGMsp3NzxOc6X"
          ]
        },
        {
          "name": "第2轮 第1日 英文原音",
          "urls": [
            "https://mgev.188766.xyz/play?migutoken=69035ae83db4d5ccca45bcd050049bfd&id=owmkmtrTcvZ8OARBvitp2lH9EHXNAompkAI8XDK4Lkd5ZkYvkXRF22SyC3KZNmDd36lYuaA6HaGXBiZXpbm%2Bq%2FeNiO%2BpxrYM67LRA9FuDSyMQf9KYU1VraeYXOCwFCy1926QxPTOTLYZUO5Y5sBxFxdNy5JXHuBrc%2BwMSslljgXXv%2FQIszy88sRfoKczf8OLOJQQHTvTZFblhLfz7t7lp7c0pubPRmPDEgKh6RD7hHvqkcb%2Fm%2FjYEsgJ82aEi4%2B6jjmrKU87QOUN0CJ60tet9ZPGRl6y1g6X%2BjoMVZpNsbx%2FOo5CTw3rhogwmKYCXcPd&name=s5eNKFdxLH5gXIHq0Dq5qcMdy9isBE%2FAFAuZfyv3AaGRbbHCFb%2F%2BqLHUYjka%2B9UtOhNqyZRAHZPLm8739TrICsaG%2F8FV%2BZSsKVePkgnW8IBpCAE28nqEOJCrj%2FpNNuZLtYiQsZV0Pa3LYD07tHNRZA%3D%3D"
          ]
        }
      ]
    },
    {
      "mgdbId": "",
      "pID": "c2a3bbe1016dba87",
      "title": "太阳vs火箭",
      "keyword": "01月06日09:00",
      "sportItemId": "2",
      "matchStatus": "2",
      "matchField": "",
      "competitionName": "NBA常规赛",
      "padImg": "http://catvod.hxfrock.ggff.net/腾讯体育.png",
      "competitionLogo": "",
      "pkInfoTitle": "太阳vs火箭",
      "modifyTitle": "NBA常规赛 太阳vs火箭",
      "presenters": "",
      "matchInfo": {
        "time": "01月06日09:00"
      },
      "nodes": [
        {
          "name": "彭磊 苏群 泱泱",
          "urls": [
            "https://mgev.188766.xyz/play?migutoken=b6cada7c0ae5bdd91256abea6d85ae38&id=g4eO7ncaMgIfAqYoQSg7QhIpcxHtYdf52coqdjmwdMKGFzsK5vEEHS3tlcIbFl5zSYXzrIz7PvKHHdRg%2FepeTJvIJ4AtUpz2DkUrd2Rg7NLRZfabQ7iCzfu4RFe4rHg%2B%2BQbUYzgAHep6exUw0CDzAuo9GrkPjjgtn0WzGGKFEGNavJ9co70xtZWKXZOW%2FRYlKhj9VyQMHAculs8eelpZaRgrIoy103Li8YNlXCdrn%2BDuP54D1hAJtVwE46lZrVdzdrBfn%2FqftjZGa8KK0u93nhJ8gJcsGQzNqFzwdgeYM0U%3D&name=yLv8dED2jONObXYw3nhkNUIdzDHzd20v0Cpn5TTDig4TWysahavZWKHJqJ%2BjU1f0uWiD%2FCir%2B6uU%2FvliZis%2B0ZvXGZ7iiCCXptRwh2XguGs%3D"
          ]
        },
        {
          "name": "英文原音",
          "urls": [
            "https://mgev.188766.xyz/play?migutoken=3fe2c00bc7fa0b5539653975c9f0af1d&id=ioT4x%2FnZmLCse6bhf06ORHvRnXvb3TjtZxGOxg%2FgnGyGzRJnWVtEbKkJtk2TPVUXxi%2Bef%2BHDBzeS4KquqbhMSO%2FeTe63BUsxs8BeKF7DWDpdXDbE%2BPz55nD%2BCTaBasBXkKo%2FvECVQA9IVpOUFMSNfckwgYXlTgbnKCanqg0wpESt5Uv69dS2%2FArf1xDAkbX3OERtlgN0uofRHANdctuak2aAMlcJ5tCOsjNNiko7xODNM7NBenhEAm66LmzAlf59Nlr%2FyXE9xbKOV%2FqWhpR%2FcW4PUZ35cd7yTYM6n8qM10Q%3D&name=sxt7uKboXqvpUYBRNat9mNMjl1ILsvdE77qEg%2BcKtX6tMQ%2FcnKjmCUdclRF4bx7UW2inbqEWjKj25gufa%2BrtacD6CEp7MNIvmAGP8DjDQN4%3D"
          ]
        }
      ]
    },
    {
      "mgdbId": "",
      "pID": "5e26c191c884ff4a",
      "title": "黄蜂vs雷霆",
      "keyword": "01月06日09:00",
      "sportItemId": "2",
      "matchStatus": "2",
      "matchField": "",
      "competitionName": "NBA常规赛",
      "padImg": "http://catvod.hxfrock.ggff.net/腾讯体育.png",
      "competitionLogo": "",
      "pkInfoTitle": "黄蜂vs雷霆",
      "modifyTitle": "NBA常规赛 黄蜂vs雷霆",
      "presenters": "",
      "matchInfo": {
        "time": "01月06日09:00"
      },
      "nodes": [
        {
          "name": "寇逸豪",
          "urls": [
            "https://mgev.188766.xyz/play?migutoken=c44ceeeba42f416266c1ff46fe78f4d4&id=g5w9JVWWlkR6%2BGtWsX%2FGJss3Xmxyuq4ySrbzatWrfxX%2B%2BgBzwFYVsJM5mxRcAI7nQYRz5tfAQGNesd6qYTr3tBocv%2BAdzyK2iKYn1SmrLlcD6zNM27s3gUhpcFjoPfWHKERtbBvBZNWAeiW%2FCA0AlO9QtlYpxOMo22LSGQ5e5frgIn75FQwd%2BpVSMrUEYvQ2KNTlFsWKGMlA0TOGjAsoMk%2BBxMefJJaoX%2BzYrywcVT6aFlC7vO16vsckLtwaOj1ebyKBaInpN0%2BVOJfGx2hjnvv%2Fvx2X6BXbs%2B9aW5uvabQ%3D&name=mFNxX61eAznYwNoUaH%2FN3GHrG6eS9ljm3ASedplmWFMSF%2BebO02AJ5mrVHPCrhcJ%2BWQDmO5K2qi%2BNsWDArPV3LSI0rvsOmkDstLyG5NdQko%3D"
          ]
        },
        {
          "name": "英文原音",
          "urls": [
            "https://mgev.188766.xyz/play?migutoken=54da43ae8cc8b6efdcf9274ea8384c1a&id=3RP6eOy1f0nvh03sZ64DRPaesbyKffhk1SwEntdxl81sjJNoEzeM7QRkxZC%2Fu2SiycW%2BLjXYOXgqgyin4sJ8R7m6xOUr6R8gZtL7Ktfkkj%2BnGzBvDrcIpLLVUEAR0YZ0lOjL6J2qRNeaTt7UaNp3UVW79qOhexsIULligK1%2FqayhzrQ1FiRAo6QaIE%2BFKi6X%2FQ7CB1N%2BD1PNWYSQEfR%2Fg9Zu6mmqIiMz5EbFGCiTfiwZe9sHED4C%2ByN10flqPzxwtlgPmCaJswipSX9RFXGhmF8gU%2B0dgeQzU6zCdkmjjWw%3D&name=%2BI9ecH9QYeGlz%2BV00Nj7ET9hpj1Sv7d5UfC95H2ixItXwl94NT6tdS8kQ26ZV0ScSklLfIpVkKvlQt4IMCSGFZTzUqy0xeWf898t%2B5pVat0%3D"
          ]
        }
      ]
    },
    {
      "mgdbId": "",
      "pID": "d17a6abedc63d18a",
      "title": "凯斯勒vs凯斯",
      "keyword": "01月06日09:05",
      "sportItemId": "3",
      "matchStatus": "2",
      "matchField": "",
      "competitionName": "WTA500布里斯班站1/16决赛",
      "padImg": "http://catvod.hxfrock.ggff.net/腾讯体育.png",
      "competitionLogo": "",
      "pkInfoTitle": "凯斯勒vs凯斯",
      "modifyTitle": "WTA500布里斯班站1/16决赛 凯斯勒vs凯斯",
      "presenters": "",
      "matchInfo": {
        "time": "01月06日09:05"
      },
      "nodes": [
        {
          "name": "凯斯勒vs凯斯",
          "urls": [
            "https://mgev.188766.xyz/play?migutoken=f16be9af0982e649692458ad3a936e42&id=KHgstA9J%2FOEuiEPjja0paTq2bBJznm88cQCmm8fvTfDq9PVYtHQHdy8T0fSkd2M6Hbw1jvSr2hYi7sze%2BHkvIqkrQ6NCsYjE4xm9ZhU1ijVZUx8y9W0tZB2gKhTC7WpYPIEi8tMSCZ1mX7tahmzIyb5WopNc8mo7dolnpfOkN65RXTRUHO1jYnVDNvJRZUq%2BPUZSwin4vhKcHt4zvc8QSR%2BCmMiUkNDktkcbBBhWxoHh78SEG%2BnwnT%2BjDuTMpWX5kyDxkGeUCi1PPkJ%2BSfZpEsgzWySePOmLT4%2BIWjkJxSM%3D&name=wVDOqMGLCDh5MjVaX2TR1iOAxKr4mp%2F2V7aa7uG%2B26%2FibYM39xkVu2Uf%2FDRevT4gGcVVLAb%2FkjmthIM%2Fb5SEn3v828zP%2Fg1YOAVsT%2BayapU%3D"
          ]
        }
      ]
    },
    {
      "mgdbId": "",
      "pID": "241eb97aa0b54c65",
      "title": "掘金vs76人",
      "keyword": "01月06日09:30",
      "sportItemId": "2",
      "matchStatus": "2",
      "matchField": "",
      "competitionName": "NBA常规赛",
      "padImg": "http://catvod.hxfrock.ggff.net/腾讯体育.png",
      "competitionLogo": "",
      "pkInfoTitle": "掘金vs76人",
      "modifyTitle": "NBA常规赛 掘金vs76人",
      "presenters": "",
      "matchInfo": {
        "time": "01月06日09:30"
      },
      "nodes": [
        {
          "name": "金浩霆",
          "urls": [
            "https://mgev.188766.xyz/play?migutoken=0f4c994a941bf84a77674189d934d69f&id=VF3%2BAoxx%2BpXvc2BBjjLUZDgTxpIhxSTMyJCeBSw6BTx6PLY9sqkTxwOJXYBUZLLJz3E6%2FjqDd66fqYYedu4LRec8FGtcORk%2FYWUEsstdAdtF2TN31mSQmiix%2FuJgi6FALn%2BA3DvIT9E6yGgN7zW4br0LmctVUcYYdkeBhDjKwB9KZ5XPlt5JewiWVa6ECYvwv6i2oHqw9Y46O0NdM2nabcU1ApaFwY2FamPck%2F%2FJAmJeEXa%2FeLGF8v3uI%2Bzg7g%2BDIkbYq3Nf2dqWm9xWpAzyUzT7wv7T370qw32gTjrHNEQ%3D&name=GBfPHdKggnyVkWgZ6FHSfOJghcw8QmsLGITwol2XVsoPNm8kNnQ5SczCMNyTiaclL3zSRwhLTjZ69t16i%2FvjHQQihzPz6kzVPPjMyZDnu9c%3D"
          ]
        },
        {
          "name": "英文原音",
          "urls": [
            "https://mgev.188766.xyz/play?migutoken=e4d079e02be32b4936fee64843bb91f1&id=mIQ2TuQYxo5cHAqd%2Bt%2BAKn7HPUlGHAtYhLKGOKFEtqEdPcODD6UIjEEIYk4ooE%2BP7RUU51mHKYgvt9AiIdpVIWPv%2FJMKsC8ujF8eK2UT9JaKjMoRCL%2B4IdE1wp7at5QZnaB%2FK7AJwCC2rDdcpPTG7JNq7pqB6rVUJfJ2sypptR7nEMkamXE8IwbMU4dm86pduKxF1wxBgoKvpx7ZThHZSCA8IGz6iXYFdtHQ0IomwiZdo134Vc2qYGuRtztSbz3qoW3E5W8rVt0ObkgAycFlL%2F6Gbg5O9PTZ6ZjFQzQ7psc%3D&name=0XB7rc4RuvnKkP9tZ6LIo76Ac%2BeZgJRXbjU1%2FQuHOu9Bfr15TqH1BOci51%2B8XIrTZ959ZsU9VGsWSaG8w3GG6adyj9nMyp%2FsOuvGhkfDMaM%3D"
          ]
        }
      ]
    },
    {
      "mgdbId": "",
      "pID": "6fc35e37dc143f3a",
      "title": "[早安Tip_Off]第75期",
      "keyword": "01月06日10:30",
      "sportItemId": "2",
      "matchStatus": "2",
      "matchField": "",
      "competitionName": "篮球直播节目",
      "padImg": "http://catvod.hxfrock.ggff.net/腾讯体育.png",
      "competitionLogo": "",
      "pkInfoTitle": "[早安Tip_Off]第75期",
      "modifyTitle": "篮球直播节目 [早安Tip_Off]第75期",
      "presenters": "",
      "matchInfo": {
        "time": "01月06日10:30"
      },
      "nodes": [
        {
          "name": "孔祥宇 殳海 辰辰",
          "urls": [
            "https://mgev.188766.xyz/play?migutoken=e9c6b024be0c6ff50bf2bdd8df1b0a78&id=z6VdLSoZrbgVRzrKIX7zr1%2FjpEpx0e4x7GIISB0zHBeJkyMlrxDHL4s9NApVI7ePb9U8G7oQQvOzWYdvObIDHrZNTsVVXlbBz1IxyRuprnchc5U13578NP%2BEcavOXtBO3GCoUTJczgXmg2BTkfo31TIwag5cBXYi7f8pe4bgC38Gq4NPpa4TELKRAqXzFnsBEEy4xtazmErsgckcdeaxLctAjJZa8gHWyTN6lovf%2FxQ38d5jFFrNlVcXLsLMhR53WZTlqY5fG8uboXbpbCJCDPPAzXz1N%2Bo8EEqpDHz7%2BLw%3D&name=nrOsz2wrdTDXp4a6aigfzDcA9jcbjHEiLrXPhHjvDQg2GPRwGoHDJU0ktEvxBznG1XGobNdL23MVTxHFgMHkyNiR9xLtvmlyYOSu74OdCHrD5YjK4b1W3so6Vl%2BjiYi85mktWXcHL0pD1iSX1aGO9Q%3D%3D"
          ]
        }
      ]
    },
    {
      "mgdbId": "",
      "pID": "169c1114b7031c4c",
      "title": "萨巴伦卡vs布克沙",
      "keyword": "01月06日10:55",
      "sportItemId": "3",
      "matchStatus": "2",
      "matchField": "",
      "competitionName": "WTA500布里斯班站1/16决赛",
      "padImg": "http://catvod.hxfrock.ggff.net/腾讯体育.png",
      "competitionLogo": "",
      "pkInfoTitle": "萨巴伦卡vs布克沙",
      "modifyTitle": "WTA500布里斯班站1/16决赛 萨巴伦卡vs布克沙",
      "presenters": "",
      "matchInfo": {
        "time": "01月06日10:55"
      },
      "nodes": [
        {
          "name": "萨巴伦卡vs布克沙",
          "urls": [
            "https://mgev.188766.xyz/play?migutoken=ddbac1e806923022f86b00061a8c8e3c&id=vrZZb29GIg1aBPXANQFh3HdA4AYCXVU7z5FFph4Ano%2Bf4MQunqyQCgHIuUP3Dm6upuxs5QoPcL5%2Baz52tP9PO960ekhEWDaPv3AkVq89UhZ2E2T9ywcIidgpF8qtdp2mDPFegtciprI7%2F0iFkLuX5Hxf0TaTxHbWHIlcXAmkFVjkpeokCNnJ8QLtaUUknG4gevSiy9X3BX%2FI2YXZTpqyMnJjGWiSymRDOHvhQtm5Zt9vV71k4Rk3cBW9MiQN7QZx7d28pBv6EWQwfi7bOTUbDGS1CBxYdMAnKuX7xGW69e4%3D&name=HbxtsUMK6IqgF8IhwJVyP2dkfJbpNLtEoa2UNjxhnT1DSHjJPz%2Bw71H%2B2mWsOOg0%2Fx4K2ZAUwOTWdZLqFVNUK97tsAmdNpUW8Y%2BeRpfYsIkZLSdU%2BoGoYcbvULGK0oY3"
          ]
        }
      ]
    },
    {
      "mgdbId": "",
      "pID": "b130704171eb9db7",
      "title": "勇士vs快船",
      "keyword": "01月06日11:00",
      "sportItemId": "2",
      "matchStatus": "2",
      "matchField": "",
      "competitionName": "NBA常规赛",
      "padImg": "http://catvod.hxfrock.ggff.net/腾讯体育.png",
      "competitionLogo": "",
      "pkInfoTitle": "勇士vs快船",
      "modifyTitle": "NBA常规赛 勇士vs快船",
      "presenters": "",
      "matchInfo": {
        "time": "01月06日11:00"
      },
      "nodes": [
        {
          "name": "孔祥宇 殳海 辰辰",
          "urls": [
            "https://mgev.188766.xyz/play?migutoken=4ebdbde8fd3c4a8dcd13115af9c20cd9&id=ncHNq7G9fkLf8zYTqgHhgHfDySDOTu24MP9CPhC55eiV0b52bDCLkg%2BJf3TTTv4GLLulPJ5PrJ%2BfJZWorgm9sOHDC5lUQdPVslmJql7As4VpA2eWoupgrAvGNoqEuAZDqD05jWCwVeEauTS2xPKMoOOHKSPrA1rKkC74L9LAf5Ni5IQkYy7eqJe5%2BHm0sBLW5Z4zeY542Q6P3uo4H3fUEnCB6s2RWAddVlDBZoMMb6ReVW8KLpedUp%2BXAIt1wQCbGFdAepymiBQhBkXyc8%2BuWZefUF6Ax3oLed8z4GdTffU%3D&name=AHOEQINWGfqu6bvyz2haH2EXUljL1AEq%2F7jVe0yM9PPFxDGlmAUbvOx%2BLveJOlujR7Q3j1s5wW9STxx19nY3P6nhEksb%2BgV%2BbE1GqICOt2ahn1NHATzJ4tEvgAbcYAeo"
          ]
        },
        {
          "name": "英文原音",
          "urls": [
            "https://mgev.188766.xyz/play?migutoken=22c2b7590e49ff3298b5f14df0be2256&id=VreZ%2FDrbFQOcTUMioIdk0JBBkI0nT8USaUconPCYFabcr3gnKmxH4UPHvJCu3Px3ZVm03pHRaQOnPvHwme9xLI070PdqamrjbksLnYJlOx6us1NYshpL8ebAkIb0uADPfCDIr6M8lehkvai7pdMVcrznr09v3fBi8jeJrW3Hw5Tn1Ca9TgR%2F30JDUVKtyrGLJJSixWRaFQgXGy1rZtCpDzgLqjfQXFWQEp2i%2BBIOBIPXW7c18XwoQAsUigo2H9Jgqp2sNtlFfdDkm%2FMOtaK9%2BjopIkGPzG5Es%2F%2FkgtIdK1Q%3D&name=1q2jemcCYnIkOXD9JcWq9PKi3sTRFX6kjeR0wQUEEUKYFy2CevNLozkaZNZzQlsj3bhmb%2FULA%2FJq6M%2BiYh%2B6RFtMvzuxu%2BX%2B%2FqrOtHl10R0%3D"
          ]
        },
        {
          "name": "二路_皓篮球",
          "urls": [
            "https://mgev.188766.xyz/play?migutoken=ee60fbbdf4d4fa0448a77ac224c00233&id=CPetg%2BR20rW%2BZdTDbJIcr%2FRrsd2r9datDETqZtGjBCCGA8uaIYxSgl%2Fq%2FHHQuBhx1sOsOMq2LKEk4CHogxj8mB9TdVxzb3VzCnLZIqewKv%2BxwgrCGXbxkqlaOO1vAk4m6LigxBN9NiF2c70Rg9p0graKL0aaR8JpW7zzo95%2FusnSwtFQXxHoRkZmHhrxCfVrAbJr7G%2BSRfkwcTbX0IOGNDMBWRjFasl%2B6BDqmgwlxBE2vBlFN1pr%2Fmltw%2FS8eh06y5654BiIKhfFb4sVpre86LdpMyBk8IWItUVaM71T1DQ%3D&name=spC9DNerKfc3GIQvE6v4yj9PY5RkqlpRVQBMkV92CAjodM6mZQdtEhdS1Tx3M2XrCT1hf762UkjpHLkCrefgvn63mRLSj%2BQupqsNP4GSBNs%3D"
          ]
        }
      ]
    },
    {
      "mgdbId": "",
      "pID": "f0bba4b777964981",
      "title": "爵士vs开拓者",
      "keyword": "01月06日11:00",
      "sportItemId": "2",
      "matchStatus": "2",
      "matchField": "",
      "competitionName": "NBA常规赛",
      "padImg": "http://catvod.hxfrock.ggff.net/腾讯体育.png",
      "competitionLogo": "",
      "pkInfoTitle": "爵士vs开拓者",
      "modifyTitle": "NBA常规赛 爵士vs开拓者",
      "presenters": "",
      "matchInfo": {
        "time": "01月06日11:00"
      },
      "nodes": [
        {
          "name": "柯凡 管维佳 婧雯",
          "urls": [
            "https://mgev.188766.xyz/play?migutoken=76e4c01c59a2a7f9712e937a22ef480b&id=OLjUk7amEcAlVM%2BOQWBNrmSnaAOBLyM8sWto81D%2FGSTBPLdt6u%2BTX8Lfp90pQH2CYoWfBDsEH7JnMcaMNUaNp7CRDwTOFpXfxeCEmnne6nq1gqTKa0VXFgggVSG8ep5Vngzkqq01%2FtUytLqoorpuqppu28fTqnzGmwSAeCYyqm5azRJDj5I6sOi8z1N5yy2c7VjvcA46hSbvfJXAnnzZPWCChjRPAVraUl2BH5wLyqr0BH9E2%2BSJ2JGqj7yNqyBlO8m8ixYDUk1PFdobdLcrV0NVRUhTl7ZSiCyK4xYRrBw%3D&name=KdOC8H46e9VUE8NgnY54tO4c2LotupfJjrZKzjtlDOmeUZcZ0cFHCEph7XWMq8LeUysS%2BaM5jbQ31FOfP4GYAAhdgWiivBTPCI4Xe2CWYVf1LewW38rWUscTQfwbLbwF"
          ]
        },
        {
          "name": "英文原音",
          "urls": [
            "https://mgev.188766.xyz/play?migutoken=e342306c95e9f75b8a9f8bc31514dd40&id=Iw%2FZlPQ%2FT%2Fb0pnj5uQKWpWVrZcHUdQkcuid%2Bbnk7wDUWBXXb8sdK%2FjJBQxXZGpPGD8rWSU0aGQpIZb8y5bI4OqtueVLFSkljBFDLKkE2lKTlIFFdi6lNBr36Hsv1xsg6nsxvgskRv1jk8Sm%2FDSFn4sZVv5W%2FJPEsY63bLc9dFRrmi5GdgR9s98ZrluaOu1gWCEQLPynssLmtbr8jLnrtWIUP2lqLtN3eWqNzp09mjnMycJKzktiFeeSyJumWZ1RXuytK2mOz%2BbzHn%2F%2FjsjuzDCq%2FN5hYVhuTdY2JOXiWboI%3D&name=1fmOMlJUFK7dVorX3acCOGyWBfvsyRPbLjIqHiyKZ3ZB760sWeLXX%2BEtkz3eQCtEkF%2BjsnS%2Fq%2BFIRI6IuvRoLkhuoLNufr3r%2FR55MZNbDS8%3D"
          ]
        }
      ]
    },
    {
      "mgdbId": "",
      "pID": "5da77c1de4f2a9c1",
      "title": "NBA常规赛精彩回顾：勇士vs快船",
      "keyword": "01月06日18:00",
      "sportItemId": "2",
      "matchStatus": "2",
      "matchField": "",
      "competitionName": "NBA经典赛",
      "padImg": "http://catvod.hxfrock.ggff.net/腾讯体育.png",
      "competitionLogo": "",
      "pkInfoTitle": "NBA常规赛精彩回顾：勇士vs快船",
      "modifyTitle": "NBA经典赛 NBA常规赛精彩回顾：勇士vs快船",
      "presenters": "",
      "matchInfo": {
        "time": "01月06日18:00"
      },
      "nodes": [
        {
          "name": "NBA常规赛精彩回顾：勇士vs快船",
          "urls": [
            "https://mgev.188766.xyz/play?migutoken=b3cbbf9747685fdb95a89c591ef9dbbe&id=v6iLw6KwFpHPMWQtrjVKRHRln0gc3H1V5Nhoizu76ZlAyikGIYgQxpx2OlDOUQCRKiyIfh0U0Tp%2Bk%2BJ5ND6yNJC%2B%2BE6TXzOY3Vn5Ehxuy4fw5hmwDE5%2B%2FwMkWOd%2BXCoCiCEKfKjwPZtCkt0PR4RHy5Ykwmg8CN1A8qBi6Odv14cNtZ4HwDltuERPMOQUP88%2BEhGHfMErkYKvrLfyku63q411L5rhE9r%2B%2Fwcgs5BzEMUXgiRvNSkSQPk%2BGlP0NcYlwCuk6xPoVqE4vu7IOf2o8fZkmQ2uzQ199VFZwZ6aXY4lFtSeXbTdS4sLip%2FSfvQ4&name=AdGGthgIMxkhaR5rJHhHGs09kUEJlNGeE4rHSVsMHA9l5KkqECht%2BdecmjLjH7WKbPncRC8kKofLEo%2FJCI1GuDhJDGDiGxmd4q%2BMMbIHfjMsF%2BVQtqJoaYfJKOjuDAaR"
          ]
        }
      ]
    },
    {
      "mgdbId": "",
      "pID": "da4ae0c9ab40e0c8",
      "title": "天津渤海银行vs河南双汇",
      "keyword": "01月06日19:00",
      "sportItemId": "4",
      "matchStatus": "2",
      "matchField": "",
      "competitionName": "女排超联赛A级双循环赛",
      "padImg": "http://catvod.hxfrock.ggff.net/腾讯体育.png",
      "competitionLogo": "",
      "pkInfoTitle": "天津渤海银行vs河南双汇",
      "modifyTitle": "女排超联赛A级双循环赛 天津渤海银行vs河南双汇",
      "presenters": "",
      "matchInfo": {
        "time": "01月06日19:00"
      },
      "nodes": [
        {
          "name": "天津渤海银行vs河南双汇",
          "urls": [
            "https://mgev.188766.xyz/play?migutoken=16ec5f5e6afbf23e0ad67e3997b9fffd&id=v1XVcXJlwv080zvSvu3XCYMTj%2BY7p4wdlhfz6xQaRYu%2BghkWgifYNUbCuQPf1KNoNQKYFH%2BwR7XWnZadoiIGVViBqv2H0oZluSQRoCx4Z9MuF8V2epL3wFqNNeVKB%2FIp4YSYrk4Sdyzl7ftCtAltTzOIziuRF5CPreQyc5boO%2Fco%2F8ArAual2U1XwhPeWLxyWmb6I428gT9NG9w0hnaB6Hz%2F1iCxrS6RqkTFmKw8HgL5bEqF74FYvd2ucBRCsZ2ZCwOIU9uXfihXbq0RhaFuPOHiXU3q%2BIYD%2FCqCy9jKh7hkIm%2Btk5BBlKwUvXXsMJ98&name=Gx4cAtE6KyPiMLIj9p3Cx0I1rVoqajWEzdsUGLBA6OxuU58HQY%2FK3U39%2B1l%2FjCBgxeqAoa4JTHLNdkQcF1Z34S9dudDRZufR24HpI8R%2FSljqdolZdeom4NitTUYqBeuT"
          ]
        }
      ]
    },
    {
      "mgdbId": "",
      "pID": "351bdfa7b95ab248",
      "title": "25_26赛季女排超级联赛常规赛：河北vs四川",
      "keyword": "01月06日19:00",
      "sportItemId": "4",
      "matchStatus": "2",
      "matchField": "",
      "competitionName": "女排超联赛双循环赛",
      "padImg": "http://catvod.hxfrock.ggff.net/腾讯体育.png",
      "competitionLogo": "",
      "pkInfoTitle": "25_26赛季女排超级联赛常规赛：河北vs四川",
      "modifyTitle": "女排超联赛双循环赛 25_26赛季女排超级联赛常规赛：河北vs四川",
      "presenters": "",
      "matchInfo": {
        "time": "01月06日19:00"
      },
      "nodes": [
        {
          "name": "25_26赛季女排超级联赛常规赛：河北vs四川",
          "urls": [
            "https://mgev.188766.xyz/play?migutoken=12a1b701cbb94528f69bb231fb88fe53&id=o4hnuXGU6VgySuk8ZAu%2FJHhCxGkvv87%2BSIk3T63pVzmWk9CPrv%2F%2Bs1YIaV2RH8yl4U8bh0ZeKY0slbd8tJsI%2Fvw7dsUJ5YfB%2FbQBQzoiaZxbAhs%2FTRF8XljPfDybixL%2BadWOOTvVGMqf4UAWEB00dbBgp%2Forpg2eXGVaAFIYzVATfrGkuc4B%2FBsIoRhk4LDprmp3rVqkxhIwWpdsU5GQ6McCzv4BdhA1DQwzWmrFiP9tHZqOgRJfiAovo1yh%2BsuxLfhqVEy4Su6ZXt2wizJkjzKv9Uget8dcy6wadoM53Ox2nigTY8GsxJoa%2BvUoYV1m&name=WzLLHMwnk5dHpBm2ccdbhq4pFzEMlY5IHRUzfJllQgEEkEQXFDCf2b%2BROtMiJVjDjV3BgFunlBsJqPTgM%2BhwyXPoBkr6%2Ft29wQ%2FmjzPIbIMrWpn5OfNDrZloJkcgpRXChrSTCMQJT%2B%2B3fuMsE09f2xTM8lfAdRYKy8e9CM89kRk%3D"
          ]
        }
      ]
    },
    {
      "mgdbId": "",
      "pID": "8c349d74991c0eca",
      "title": "合肥狂风vs张家口体文旅",
      "keyword": "01月06日19:30",
      "sportItemId": "",
      "matchStatus": "1",
      "matchField": "",
      "competitionName": "NBL常规赛第7轮",
      "padImg": "http://catvod.hxfrock.ggff.net/腾讯体育.png",
      "competitionLogo": "",
      "pkInfoTitle": "合肥狂风vs张家口体文旅",
      "modifyTitle": "NBL常规赛第7轮 合肥狂风vs张家口体文旅",
      "presenters": "",
      "matchInfo": {
        "time": "01月06日19:30"
      },
      "nodes": [
        {
          "name": "合肥狂风vs张家口体文旅",
          "urls": [
            "https://mgev.188766.xyz/play?migutoken=38313ea010dc2596a87cf4fb7a8a9077&id=GzoQOoHEFKnmevv0DMAiWlKsQ0fRp8jhw9lQsNllxwUzqaU9PwusAovjvp99J7mK16oXBCyzDULMDPbZMKwbQhi7W%2BZtws5PDfgEHeuuVptR6L9cKZNknALufGFpn1zp5%2BqDv6AK2eg35kdTVio5tnPp34UFE2Jho4ntW%2Facpo0QjmEVE5B4SkPHIh0D5KsrmPZZ4IKOKlu94F1lHl8uBb7XSLVL31B8Zjc%2BgoqlkYauF55RVYZlMGXgzKPgUHbiaYtx%2FQgz%2Bo%2FiMSBEDKUVQQhhPfwxSVJCZjrhj9yEkRXX0loKVbey7nJxuz05KaA2&name=Nc3zveINqOhBLnDyCJjyH4AVt%2BiXoFldYqMtf02GoiINZsjwDYLqd28p7GW7lg5XF1fJyRr4dSNIo6RRwgWxB61yBRj7EYOuS1SPE2QQAvXNphZrRNE9atcwhywoQfYs"
          ]
        }
      ]
    },
    {
      "mgdbId": "",
      "pID": "22cc751a5021e507",
      "title": "北京北冰洋vs辽宁东港草莓",
      "keyword": "01月06日20:00",
      "sportItemId": "4",
      "matchStatus": "1",
      "matchField": "",
      "competitionName": "女排超联赛A级双循环赛",
      "padImg": "http://catvod.hxfrock.ggff.net/腾讯体育.png",
      "competitionLogo": "",
      "pkInfoTitle": "北京北冰洋vs辽宁东港草莓",
      "modifyTitle": "女排超联赛A级双循环赛 北京北冰洋vs辽宁东港草莓",
      "presenters": "",
      "matchInfo": {
        "time": "01月06日20:00"
      },
      "nodes": [
        {
          "name": "北京北冰洋vs辽宁东港草莓",
          "urls": [
            "https://mgev.188766.xyz/play?migutoken=383b8eed01cadbf16b95a8979ae88975&id=N%2FEMNffxd%2BqoT%2FmC3nOQ3nwPEwB1cgwrd%2BcCbwZlPkexTGuDeBLZyiLNZ8J2Rb74zkNcqyw7WDEis%2FPJpErDRxuQXkerCZ0CmqGSexmJIIlQc6AZ5lfVNTm8FrvZkFcxL0Eu0mGq2kDmN56yEmVTC2wH%2BjQUtOEHL1CiHtDOANRe7MKG0ZaH0Z9bl1I%2BdJP6H4lXXWUdEWqEQHnZZjodSygRRjC%2FFaMHAErxBxKr1ERUrlrTgVNQsDf6Xda8L0Q5FAGviTd40Ud1FIhvgQQPjyhCvRGQMGN%2BYY36t4jqPVIVeH3E%2Fd7Rf8mNptL0QQjB&name=Z0aehUcEslijNN419mE%2Fakw488CkbHNk4gZek76yFCegUl5bCeEL4LBxFT3X2FNAcyjp1uOPRG8b4vhNNalg9tY7DZ4RbfhAnXo2XYWqmHRat1Sex52wRG32pzak1F3aBQXBCm8rtTLf0Qh5h4EAMg%3D%3D"
          ]
        }
      ]
    },
    {
      "mgdbId": "",
      "pID": "39627136aba1a57b",
      "title": "NBA常规赛精彩回顾：勇士vs快船",
      "keyword": "01月06日20:00",
      "sportItemId": "2",
      "matchStatus": "1",
      "matchField": "",
      "competitionName": "NBA经典赛",
      "padImg": "http://catvod.hxfrock.ggff.net/腾讯体育.png",
      "competitionLogo": "",
      "pkInfoTitle": "NBA常规赛精彩回顾：勇士vs快船",
      "modifyTitle": "NBA经典赛 NBA常规赛精彩回顾：勇士vs快船",
      "presenters": "",
      "matchInfo": {
        "time": "01月06日20:00"
      },
      "nodes": [
        {
          "name": "NBA常规赛精彩回顾：勇士vs快船",
          "urls": [
            "https://mgev.188766.xyz/play?migutoken=6650f4f292728efcd5c6af59445f902a&id=8ZKkfWmIUI0YzD1IRWIbtvuRUsKLctg6J0PyypJK%2Bw03zL7cH5H4eeH%2Bx3S3kNZDCNUe6c%2FABWNnEhfx%2FHjNv%2FeGJVhRZAV00gC40U93UxiYkLE8Kx8jkmaEjoP69s8F1MMgA04agdqu8sfSX8RV7hcHl4GWH8eoQjZy6DwlUe9SsfDxuJbFKNjJ50AAzLRe48qyZrGI8oT54vyp4jtpxY3PJElu22VxMaH625FJLQLLCo1oaChqnrD49CpItcmLZMLAnrCL0wTxdBzVeUHYiRA%2FuyeYdjhMPTnHUdLAai83cHBSKxFaXpbbl6gHWt6M&name=sMfzEc%2BNl3igVIu2wSA0oT3f9f95nTgkBl5wXv6onDt0Ts%2BMverbOLxOmer74Pxr9hWUeQ0KYEJFhFFmlEkWqhdFJDIOWMS8eyuZmVVn7xNTOdqXqGbZjryFs5k%2F%2BHOw"
          ]
        }
      ]
    },
    {
      "mgdbId": "",
      "pID": "54aedd9fac70165b",
      "title": "25_26赛季女排超级联赛常规赛：广东vs浙江",
      "keyword": "01月06日20:00",
      "sportItemId": "4",
      "matchStatus": "1",
      "matchField": "",
      "competitionName": "女排超联赛双循环赛",
      "padImg": "http://catvod.hxfrock.ggff.net/腾讯体育.png",
      "competitionLogo": "",
      "pkInfoTitle": "25_26赛季女排超级联赛常规赛：广东vs浙江",
      "modifyTitle": "女排超联赛双循环赛 25_26赛季女排超级联赛常规赛：广东vs浙江",
      "presenters": "",
      "matchInfo": {
        "time": "01月06日20:00"
      },
      "nodes": [
        {
          "name": "25_26赛季女排超级联赛常规赛：广东vs浙江",
          "urls": [
            "https://mgev.188766.xyz/play?migutoken=527ac15a2a27abd1e3fd0d867ed070f1&id=IkFPURw6uNY%2BTYDORQVvldx8s00CRnVFgU48uGlJUbwuC7Jbzww4zYmUy89MzXZNbBtxaGGUXttbaa4eVsuqEPwe59a%2FhhdBETBccPAPIE8FeVC%2BzMPXn8uCbj7VWuULTfHlYkGORyOLdgV3vl1q7r48w1%2B3E1NTJtPqTnoW3I57K5UcdTCe7m5YRjYICpCPXcEH%2B7JZ4fktlssHrh1ePcsDYP8LqqbuligSr922yM9mrQWW7vK4RNYZMPJymrVgpupvixytHL%2FsWh%2Bn347CzNwIbpIBIuDXBqgLh4hqHXoIiw0Hu9lYTwZJ4ATrgq%2Fa&name=PNyEprNmnaRZQqtPhWp25ceirAG1PNYP6xvh%2FEcgWYzututMwjeuq9uQzpwxwir73XnFzhwRu%2FMtBlighi4y4Sa5rOvCRIqVI4pLALnWl8jZQqTalb6g4JZ7l3FAx9iJClpXjQry302gzN5d9COsHsrSeGW9jyVbl0faMLLHYrg%3D"
          ]
        }
      ]
    },
    {
      "mgdbId": "",
      "pID": "983488708402",
      "title": "抖音CBA直播间",
      "keyword": "01月06日19:30",
      "sportItemId": "2",
      "matchStatus": "1",
      "matchField": "",
      "competitionName": "CBA联赛",
      "padImg": "http://catvod.hxfrock.ggff.net/抖音CBA.png",
      "competitionLogo": "",
      "pkInfoTitle": "抖音CBA直播间",
      "modifyTitle": "",
      "presenters": "",
      "matchInfo": {
        "time": "01月06日19:30"
      },
      "nodes": [
        {
          "name": "CBA:宁波vs北京等7场比赛同播",
          "urls": [
            "http://pull-flv-f26.douyinliving.com/fantasy/stream-118623106563572567_hd.flv?arch_hrchy=s2&expire=69665007&major_anchor_level=vip&rtm_expr_tag=empty_device_type&sign=d4d56f7f0338eefcfb418f098c4a8ab1&t_id=037-20260106220039B7B5485E5BCB4531B61E-VaXlX6&unique_id=stream-118623106563572567_855_flv_hd"
          ]
        },
        {
          "name": "南京vs辽宁",
          "urls": [
            "http://pull-flv-f26.douyinliving.com/fantasy/stream-118623114540876631_hd.flv?arch_hrchy=s2&expire=69665007&major_anchor_level=vip&rtm_expr_tag=empty_device_type&sign=6a3f90687e093f609c556639fb87d173&t_id=037-20260106220039B7B5485E5BCB4531B61E-YZmZ9x&unique_id=stream-118623114540876631_855_flv_hd"
          ]
        },
        {
          "name": "龙狮vs新疆",
          "urls": [
            "http://pull-flv-f26.douyinliving.com/fantasy/stream-695083870540792663_hd.flv?arch_hrchy=s2&expire=69665007&major_anchor_level=vip&rtm_expr_tag=empty_device_type&sign=3cb5dfa07a643a60289a05a611b394e0&t_id=037-20260106220039B7B5485E5BCB4531B61E-kwVMuB&unique_id=stream-695083870540792663_855_flv_hd"
          ]
        },
        {
          "name": "山西vs四川",
          "urls": [
            "http://pull-flv-f1.douyinliving.com/fantasy/stream-406853498338804567_hd.flv?arch_hrchy=s2&keeptime=00093a80&major_anchor_level=vip&rtm_expr_tag=empty_device_type&t_id=037-20260106220039B7B5485E5BCB4531B61E-QPXXLI&unique_id=stream-406853498338804567_855_flv_hd&wsSecret=bb166d48f823c96a27099ff51bec7d88&wsTime=695d1587"
          ]
        },
        {
          "name": "福建vs山东",
          "urls": [
            "http://pull-flv-f26.douyinliving.com/fantasy/stream-118623126079144791_hd.flv?arch_hrchy=s2&expire=69665007&major_anchor_level=vip&rtm_expr_tag=empty_device_type&sign=46428622ff577255a898bc6987540ab4&t_id=037-20260106220039B7B5485E5BCB4531B61E-vei8Fy&unique_id=stream-118623126079144791_855_flv_hd"
          ]
        },
        {
          "name": "吉林vs江苏",
          "urls": [
            "http://pull-flv-f26.douyinliving.com/fantasy/stream-695083882475422551_hd.flv?arch_hrchy=s2&expire=69665007&major_anchor_level=vip&rtm_expr_tag=empty_device_type&sign=5891342be76c98f9616787ae4c285cfa&t_id=037-20260106220039B7B5485E5BCB4531B61E-h6wqGm&unique_id=stream-695083882475422551_855_flv_hd"
          ]
        },
        {
          "name": "天津vs北控",
          "urls": [
            "http://pull-f5.douyinliving.com/fantasy/stream-406853510425215831_hd.flv?arch_hrchy=s2&expire=1768312839&major_anchor_level=vip&rtm_expr_tag=empty_device_type&sign=ad8f0f086c0f64b4546a15245e0f3e06&t_id=037-20260106220039B7B5485E5BCB4531B61E-AZQgll&unique_id=stream-406853510425215831_855_flv_hd&volcSecret=ad8f0f086c0f64b4546a15245e0f3e06&volcTime=1768312839"
          ]
        },
        {
          "name": "原声:南京vs辽宁",
          "urls": [
            "http://pull-flv-f26.douyinliving.com/fantasy/stream-695083894090761047_hd.flv?arch_hrchy=s2&expire=69665007&major_anchor_level=vip&rtm_expr_tag=empty_device_type&sign=ce8feee488066a86d2aff1ed50a19eb7&t_id=037-20260106220039B7B5485E5BCB4531B61E-szxbxi&unique_id=stream-695083894090761047_855_flv_hd"
          ]
        },
        {
          "name": "原声:福建vs山东",
          "urls": [
            "http://pull-flv-f26.douyinliving.com/fantasy/stream-695083903484691287_hd.flv?arch_hrchy=s2&expire=69665007&major_anchor_level=vip&rtm_expr_tag=empty_device_type&sign=9c32377953f9e5cf2a6ae339992b4e93&t_id=037-20260106220039B7B5485E5BCB4531B61E-vmQn3q&unique_id=stream-695083903484691287_855_flv_hd"
          ]
        }
      ]
    }
  ],
  "timestamp": "2026-01-06T14:00:40.311Z",
  "shanghaiTime": "2026-01-06T22:00:40.311Z",
  "count": 20,
  "mode": "today",
  "source": "real + cba_live"
}